hardware/opcode.sv
`define NOP 8'b0000_0000
`define HLT 8'b1111_1111

`define MOV 8'b0000_0001
`define LDA 8'b0000_0010
`define STA 8'b0000_0011

`define ADD 8'b0000_0100
`define SUB 8'b0000_0101
`define MUL 8'b0000_0110
`define DIV 8'b0000_0111

`define AND 8'b0000_1000
`define OR 8'b0000_1001
`define XOR 8'b0000_1010
`define NOT 8'b0000_1011
`define RR 8'b0000_1100

`define PUSH 8'b0000_1101
`define POP 8'b0000_1110

`define JUMP 8'b1000_0000
`define CALL 8'b1010_0000
`define RET 8'b1011_0000

`define NO_REG 3'b000
`define B_REG 3'b001
`define C_REG 3'b010
`define D_REG 3'b001
`define E_REG 3'b100
`define PC_REG 3'b101
`define SP_REG 3'b110
`define A_REG 3'b111

`define NO_OP 4'b0000
`define ADD_OP 4'b0001
`define SUB_OP 4'b0010
`define MUL_OP 4'b0011
`define DIV_OP 4'b0100
`define AND_OP 4'b1000
`define OR_OP 4'b1001
`define XOR_OP 4'b1010
`define NOT_OP 4'b1011
`define RRS_OP 4'b1100
`define RRC_OP 4'b1101
`define LLS_OP 4'b1110
`define LLC_OP 4'b1111

hardware/Control.sv
`include "opcode.sv"

`timescale 1ns / 100ps
`define ROM_ADDR_SIZE 4
`define ROM_DATA_SIZE 26
`define ROM_NUM_INST_SIZE 7
`define ROM_NOTHING `ROM_NUM_INST_SIZE - 1
`define RESET 255
`define STATE_END 255

module ROM (
    input  logic [`ROM_ADDR_SIZE - 1 : 0] rom_addr,
    input  logic [                 2 : 0] read_addr,
    input  logic [                 2 : 0] write_addr,
    output logic [`ROM_DATA_SIZE - 1 : 0] CTRL
);

    logic [`ROM_DATA_SIZE - 1 : 0] read_reg_addr, write_reg_addr;

    always_comb begin
        read_reg_addr  = (read_addr == 3'b111) ? (1'b1 << 25) : ({23'b0, read_addr} << 20);
        write_reg_addr = (write_addr == 3'b111) ? (1'b1 << 24) : ({23'b0, write_addr} << 16);
    end

    // localparam logic [`ROM_DATA_SIZE * (`ROM_NUM_INST_SIZE + 1) - 1:0] memory = {
    localparam logic [`ROM_DATA_SIZE - 1 : 0] memory[`ROM_NUM_INST_SIZE] = {
        /*
         * Acc_Read, Acc_Write,
         * Reg_Read, Reg_Read_Addr[2:0], Reg_Write, Reg_Write_Addr[2:0],
         * Control_Read, Control_Write, Io_Read, IR_Write, IR_Read, MDR_Read, PC_Sel[2:0],
         * ALU_In_1, ALU_In_2, ALU_Op_Sel[3:0], ALU_Out_Write
         */

        // Fetch
        `ROM_DATA_SIZE'b0_0_0_000_0_000_1_0_0_0_0_1_001_0_0_0000_0,  // MDR <- [PC]

        // Decode & Execute
        `ROM_DATA_SIZE'b0_0_1_000_1_000_0_0_0_0_0_0_000_0_0_0000_0,  // Rd <- Rs
        `ROM_DATA_SIZE'b0_0_0_000_0_000_1_0_0_1_0_0_001_0_0_0000_0,  // IR <- data
        `ROM_DATA_SIZE'b0_0_0_000_1_000_0_0_0_0_1_0_000_0_0_0000_0,  // Rd <- IR
        `ROM_DATA_SIZE'b0_0_1_000_0_000_0_0_0_1_0_0_000_0_0_0000_0,  // IR <- Rs
        `ROM_DATA_SIZE'b0_0_0_000_1_000_1_0_1_0_0_0_000_0_0_0000_0,  // Rd <- [IR]

        // END / RESET
        `ROM_DATA_SIZE'b0_0_0_000_0_000_0_0_0_0_0_0_000_0_0_0000_0  // Nothing
    };

    assign CTRL = memory[rom_addr] | read_reg_addr | write_reg_addr;
    // assign CTRL     = memory[ `ROM_DATA_SIZE * rom_addr +: `ROM_DATA_SIZE ] | memory[ `ROM_DATA_SIZE * read_reg_addr +: `ROM_DATA_SIZE ] | memory[ `ROM_DATA_SIZE * write_reg_addr +: `ROM_DATA_SIZE ];
endmodule

module Control #(
    parameter unsigned DATA_WIDTH = 16
) (
    input logic                      reset_n,
    input logic                      clk,
    input logic [DATA_WIDTH - 1 : 0] MDR,
    input logic                      Z_flag,
    input logic                      C_flag,

    output logic         Halt,
    output logic         Acc_Read,
    output logic         Acc_Write,
    output logic         Reg_Read,
    output logic [2 : 0] Reg_Read_Addr,
    output logic         Reg_Write,
    output logic [2 : 0] Reg_Write_Addr,
    output logic         Control_Read,
    output logic         Control_Write,
    output logic         Io_Read,
    output logic         IR_Write,
    output logic         IR_Read,
    output logic         MDR_Read,
    output logic [2 : 0] PC_Sel,
    output logic         ALU_In_1,
    output logic         ALU_In_2,
    output logic [3 : 0] ALU_Op_Sel,
    output logic         ALU_Out_Write
);

    logic [`ROM_ADDR_SIZE - 1 : 0] rom_addr;
    logic [`ROM_DATA_SIZE - 1 : 0] CTRL;

    logic [2 : 0] write_addr, read_addr, param_2, param_1;
    logic param_2_immd, param_1_immd;
    logic [7 : 0] instr;

    logic [7 : 0] state, next_state;

    ROM rom (
        .rom_addr  (rom_addr),
        .read_addr (read_addr),
        .write_addr(write_addr),
        .CTRL      (CTRL)
    );

    assign {instr, param_1_immd, param_1, param_2_immd, param_2} = MDR;

    assign {Acc_Read, Acc_Write,
            Reg_Read, Reg_Read_Addr, Reg_Write, Reg_Write_Addr,
            Control_Read, Control_Write, Io_Read, IR_Write, IR_Read, MDR_Read,
            PC_Sel,
            ALU_In_1, ALU_In_2, ALU_Op_Sel, ALU_Out_Write} = CTRL;

    always_ff @(posedge clk) begin
        if (!reset_n) state <= `RESET;
        else state <= next_state;
    end

    always_ff @(posedge clk) begin
        if (!reset_n) Halt <= 0;
        else if ((state == `STATE_END) && (instr == `HLT)) Halt <= 1;
    end

    always_comb begin
        if (!Halt) begin
            case (state)
                // Fetch
                0: begin
                    rom_addr   = 0;
                    write_addr = 0;
                    read_addr  = 0;
                    next_state = 1;
                end

                // Decode & Execute
                1: begin
                    case (instr)
                        `NOP: begin
                            rom_addr   = `ROM_NOTHING;
                            write_addr = 0;
                            read_addr  = 0;
                            next_state = `STATE_END;
                        end
                        `HLT: begin
                            rom_addr   = `ROM_NOTHING;
                            write_addr = 0;
                            read_addr  = 0;
                            next_state = `STATE_END;
                        end
                        `MOV: begin
                            if (param_2_immd == 1'b1) begin
                                rom_addr   = 2;
                                write_addr = 0;
                                read_addr  = 0;
                                next_state = 2;
                            end else begin
                                rom_addr   = 1;
                                write_addr = param_1;
                                read_addr  = param_2;
                                next_state = `STATE_END;
                            end
                        end
                        `LDA: begin
                            rom_addr   = (param_2_immd == 1'b1) ? 2 : 4;
                            write_addr = 0;
                            read_addr  = param_2;
                            next_state = 2;
                        end
                        default: begin
                            rom_addr   = `ROM_NOTHING;
                            write_addr = 0;
                            read_addr  = 0;
                            next_state = `STATE_END;
                        end
                    endcase
                end
                2: begin
                    case (instr)
                        `MOV: begin
                            rom_addr   = 3;
                            write_addr = param_1;
                            read_addr  = 0;
                            next_state = `STATE_END;
                        end
                        `LDA: begin
                            rom_addr   = 5;
                            write_addr = param_1;
                            read_addr  = 0;
                            next_state = `STATE_END;
                        end
                        default: begin
                            rom_addr   = `ROM_NOTHING;
                            write_addr = 0;
                            read_addr  = 0;
                            next_state = `STATE_END;
                        end
                    endcase
                end

                // End / Reset Cycle
                `RESET: begin
                    rom_addr   = `ROM_NOTHING;
                    write_addr = 0;
                    read_addr  = 0;
                    next_state = 0;
                end

                default: begin
                end
            endcase
        end
    end

endmodule

hardware/Register.sv
`timescale 1ns / 100ps

typedef struct packed {
    logic [16 - 1 : 0] SP;
    logic [16 - 1 : 0] PC;
    logic [16 - 1 : 0] E_reg;
    logic [16 - 1 : 0] D_reg;
    logic [16 - 1 : 0] C_reg;
    logic [16 - 1 : 0] B_reg;
} register_def_t;

typedef union packed {
    register_def_t    reg_list;
    logic   [ 6 * 16 - 1 : 0 ] reg_array;
} register_file_t;

module Register #(
    parameter unsigned DATA_WIDTH = 16
) (
    input                             clk,
    input  logic                      write,
    input  logic                      read,
    input  logic                      reset_n,
    input  logic [             2 : 0] addr_read,
    input  logic [             2 : 0] addr_write,
    input  logic [DATA_WIDTH - 1 : 0] data_write,
    output logic [DATA_WIDTH - 1 : 0] data_read
);

    register_file_t register_file;

    // debug
    logic [16 - 1 : 0] B_reg_debug;
    logic [16 - 1 : 0] C_reg_debug;
    logic [16 - 1 : 0] D_reg_debug;
    logic [16 - 1 : 0] E_reg_debug;
    // logic [4 * 16 - 1 : 0] reg_array_debug;

    assign B_reg_debug = register_file.reg_list.B_reg;
    assign C_reg_debug = register_file.reg_list.C_reg;
    assign D_reg_debug = register_file.reg_list.D_reg;
    assign E_reg_debug = register_file.reg_list.E_reg;
    // assign reg_array_debug = register.reg_array;

    always @(posedge clk) begin
        if (!reset_n) register_file <= 'b0;
        else if (write && (addr_write != 'b0))
            register_file[DATA_WIDTH*(addr_write-1)+:DATA_WIDTH] <= data_write;
    end

    assign data_read = (read && (addr_read != 'b0))
                        ? register_file[DATA_WIDTH * ( addr_read - 1 ) +: DATA_WIDTH]
                        : {DATA_WIDTH {1'hz}};

endmodule

hardware/Processor.sv
`timescale 1ns / 100ps

module Processor #(
    parameter unsigned ADDR_WIDTH = 16,
    parameter unsigned DATA_WIDTH = 16
) (
    output logic [ADDR_WIDTH - 1 : 0] address,
    inout  logic [DATA_WIDTH - 1 : 0] data,
    output bit                        read_mem,
    output bit                        write_mem,
    input  bit                        reset_n,
    input  logic                      clk
);

    ////////////////////////  Declaration & Inittialization  ///////////////////////////////
    // Registers & flags
    reg [ADDR_WIDTH - 1 : 0] PC_debug, SP_debug;
    reg [DATA_WIDTH - 1 : 0] MDR, IR, Acc;
    logic Z_flag, C_flag;

    let PC = register.register_file.reg_list.PC;
    let SP = register.register_file.reg_list.SP;
    assign PC_debug = PC;
    assign SP_debug = SP;

    // control signals
    logic Halt;
    logic Acc_Write, Acc_Read, Reg_Write, Reg_Read;
    logic [2 : 0] Reg_Read_Addr, Reg_Write_Addr;
    logic Control_Read, IR_Write, IR_Read, MDR_Read, Io_Read, Control_Write;
    wire [2 : 0] PC_Sel;
    logic ALU_In_1, ALU_In_2, ALU_Out_Write;
    logic [3 : 0] ALU_Op_Sel;

    // interconnect wires & reg
    wire [DATA_WIDTH - 1 : 0] internal_databus;
    logic [ADDR_WIDTH - 1 : 0] next_pc;
    logic [DATA_WIDTH - 1 : 0] ALU_Src_A, ALU_Src_B, ALU_out;

    // ALU
    // Alu alu (
    //     .A_reg     (ALU_Src_A),
    //     .B_reg     (ALU_Src_B),
    //     .op_select (ALU_Op_Sel),
    //     .ALU_output(ALU_out),
    //     .Z_flag    (Z_flag),
    //     .C_flag    (C_flag)
    // );

    // Register File
    Register register (
        .write     (Reg_Write),
        .read      (Reg_Read),
        .reset_n   (reset_n),
        .clk       (clk),
        .data_read (internal_databus),
        .data_write(internal_databus),
        .addr_read (Reg_Read_Addr),
        .addr_write(Reg_Write_Addr)
    );

    // Control Unit
    Control control (
        .reset_n       (reset_n),
        .clk           (clk),
        .MDR           (MDR),
        .Halt          (Halt),
        .Acc_Read      (Acc_Read),
        .Acc_Write     (Acc_Write),
        .Reg_Write     (Reg_Write),
        .Reg_Read      (Reg_Read),
        .Control_Read  (Control_Read),
        .Control_Write (Control_Write),
        .Io_Read       (Io_Read),
        .IR_Write      (IR_Write),
        .IR_Read       (IR_Read),
        .MDR_Read      (MDR_Read),
        .PC_Sel        (PC_Sel),
        .Z_flag        (Z_flag),
        .C_flag        (C_flag),
        .ALU_In_1      (ALU_In_1),
        .ALU_In_2      (ALU_In_2),
        .ALU_Op_Sel    (ALU_Op_Sel),
        .ALU_Out_Write (ALU_Out_Write),
        .Reg_Read_Addr (Reg_Read_Addr),
        .Reg_Write_Addr(Reg_Write_Addr)
    );

    ////////////////////////////////////////////////////////////////////////////////////////

    ////////////////////////  Memory Access  ////////////////////////////

    assign read_mem  = Control_Read ? 1 : 0;
    assign write_mem = Control_Write ? 1 : 0;
    always_latch begin
        if (MDR_Read) MDR = internal_databus;
        if (IR_Write) IR = internal_databus;
        if (Acc_Write && Reg_Write) Acc = internal_databus;
    end

    assign internal_databus = read_mem ? data
                                : (ALU_Out_Write ? ALU_out
                                    : (IR_Read ? IR
                                        : ((Acc_Read && Reg_Read) ? Acc
                                            : {DATA_WIDTH {1'hz}})));

    assign address = Control_Read ? (Io_Read ? IR : PC) : (Control_Write ? IR : {ADDR_WIDTH{1'hz}});
    assign data = write_mem ? internal_databus : {DATA_WIDTH{1'hz}};

    //////////////////////////////////////////////////////////////////////

    ////////////////////////  ALU  ////////////////////////////

    // always_comb begin
    //     case (ALU_In_1)
    //         1: ALU_Src_A = internal_databus;
    //         default: begin
    //             ALU_Src_A = {DATA_WIDTH{1'b0}};
    //         end
    //     endcase
    //     case (ALU_In_2)
    //         0: ALU_Src_B = internal_databus;
    //         1: ALU_Src_B = IR;
    //         default: begin
    //             ALU_Src_B = {DATA_WIDTH{1'b0}};
    //         end
    //     endcase
    // end

    ///////////////////////////////////////////////////////////

    ////////////////////////  CPU reset Program Counter ////////////////////////////

    always_comb begin
        case (PC_Sel)
            0:       next_pc = PC + {ADDR_WIDTH{1'b0}};
            1:       next_pc = PC + 1'b1;
            2:       next_pc = Z_flag ? IR : PC + 1'b1;
            3:       next_pc = (!Z_flag) ? IR : PC + 1'b1;
            4:       next_pc = (C_flag) ? IR : PC + 1'b1;
            5:       next_pc = (!C_flag) ? IR : PC + 1'b1;
            default: next_pc = PC + {ADDR_WIDTH{1'b0}};
        endcase
    end

    always_ff @(posedge clk) begin
        if (!reset_n) PC <= {ADDR_WIDTH{1'b0}};
        else if (!Halt) PC <= next_pc;
    end

    //////////////////////////////////////////////////////////////////////

endmodule

hardware/Memory.sv
`timescale 1ns / 100ps

module Memory #(
    parameter unsigned ADDR_WIDTH = 16,
    parameter unsigned DATA_WIDTH = 16,
    parameter unsigned DEPTH = 2 ** ADDR_WIDTH
) (
    input logic                      clk,
    input bit                        write,
    input bit                        read,
    input logic [ADDR_WIDTH - 1 : 0] addr,
    inout logic [DATA_WIDTH - 1 : 0] data
);

    logic [DATA_WIDTH - 1 : 0] read_addr;
    logic [DATA_WIDTH - 1 : 0] mem[16];

    always_comb begin
        if (write) mem[addr] = data;
        if (read) read_addr = addr;
    end

    assign data = read ? mem[read_addr] : {DATA_WIDTH{1'hz}};
endmodule

hardware/test_benches/Processor_tb.sv
`timescale 1ns / 100ps

module Processor_tb;
    parameter unsigned ADDR_WIDTH = 16;
    parameter unsigned DATA_WIDTH = 16;


    logic clk, read, write, reset_n;
    logic [ADDR_WIDTH-1:0] addr;
    wire  [DATA_WIDTH-1:0] data;

    Memory memory (
        .write(write),
        .read (read),
        .clk  (clk),
        .addr (addr),
        .data (data)
    );

    Processor u0 (
        .address  (addr),
        .data     (data),
        .read_mem (read),
        .write_mem(write),
        .clk      (clk),
        .reset_n  (reset_n)
    );



    always #1 clk = ~clk;

    initial begin
        clk     = 1;
        reset_n = 1;
        $readmemh("memory.hex", memory.mem, 0);

        #5 reset_n = 0;
        #5 reset_n = 1;

        #50 $finish;
    end
    initial begin
        $dumpfile("waveform.vcd");
        $dumpvars;
    end

endmodule

hardware/test_benches/waveform.vcd
$version Generated by VerilatedVcd $end
$timescale 100ps $end
 $scope module TOP $end
  $scope module Processor_tb $end
   $var wire 32 e ADDR_WIDTH [31:0] $end
   $var wire 32 e DATA_WIDTH [31:0] $end
   $var wire 1 ` clk $end
   $var wire 1 3 read $end
   $var wire 1 4 write $end
   $var wire 1 a reset_n $end
   $var wire 16 M addr [15:0] $end
   $var wire 16 b data [15:0] $end
   $scope module memory $end
    $var wire 32 e ADDR_WIDTH [31:0] $end
    $var wire 32 e DATA_WIDTH [31:0] $end
    $var wire 32 f DEPTH [31:0] $end
    $var wire 1 ` clk $end
    $var wire 1 4 write $end
    $var wire 1 3 read $end
    $var wire 16 M addr [15:0] $end
    $var wire 16 b data [15:0] $end
    $var wire 16 N read_addr [15:0] $end
    $var wire 16 # mem[0] [15:0] $end
    $var wire 16 $ mem[1] [15:0] $end
    $var wire 16 % mem[2] [15:0] $end
    $var wire 16 & mem[3] [15:0] $end
    $var wire 16 ' mem[4] [15:0] $end
    $var wire 16 ( mem[5] [15:0] $end
    $var wire 16 ) mem[6] [15:0] $end
    $var wire 16 * mem[7] [15:0] $end
    $var wire 16 + mem[8] [15:0] $end
    $var wire 16 , mem[9] [15:0] $end
    $var wire 16 - mem[10] [15:0] $end
    $var wire 16 . mem[11] [15:0] $end
    $var wire 16 / mem[12] [15:0] $end
    $var wire 16 0 mem[13] [15:0] $end
    $var wire 16 1 mem[14] [15:0] $end
    $var wire 16 2 mem[15] [15:0] $end
   $upscope $end
   $scope module u0 $end
    $var wire 32 e ADDR_WIDTH [31:0] $end
    $var wire 32 e DATA_WIDTH [31:0] $end
    $var wire 16 M address [15:0] $end
    $var wire 16 b data [15:0] $end
    $var wire 1 3 read_mem $end
    $var wire 1 4 write_mem $end
    $var wire 1 a reset_n $end
    $var wire 1 ` clk $end
    $var wire 16 U PC_debug [15:0] $end
    $var wire 16 V SP_debug [15:0] $end
    $var wire 16 E MDR [15:0] $end
    $var wire 16 F IR [15:0] $end
    $var wire 16 G Acc [15:0] $end
    $var wire 1 g Z_flag $end
    $var wire 1 h C_flag $end
    $var wire 1 W Halt $end
    $var wire 1 5 Acc_Write $end
    $var wire 1 6 Acc_Read $end
    $var wire 1 7 Reg_Write $end
    $var wire 1 8 Reg_Read $end
    $var wire 3 9 Reg_Read_Addr [2:0] $end
    $var wire 3 : Reg_Write_Addr [2:0] $end
    $var wire 1 3 Control_Read $end
    $var wire 1 ; IR_Write $end
    $var wire 1 < IR_Read $end
    $var wire 1 = MDR_Read $end
    $var wire 1 > Io_Read $end
    $var wire 1 4 Control_Write $end
    $var wire 3 ? PC_Sel [2:0] $end
    $var wire 1 @ ALU_In_1 $end
    $var wire 1 A ALU_In_2 $end
    $var wire 1 B ALU_Out_Write $end
    $var wire 4 C ALU_Op_Sel [3:0] $end
    $var wire 16 c internal_databus [15:0] $end
    $var wire 16 d next_pc [15:0] $end
    $var wire 16 i ALU_Src_A [15:0] $end
    $var wire 16 j ALU_Src_B [15:0] $end
    $var wire 16 k ALU_out [15:0] $end
    $scope module control $end
     $var wire 32 e DATA_WIDTH [31:0] $end
     $var wire 1 a reset_n $end
     $var wire 1 ` clk $end
     $var wire 16 E MDR [15:0] $end
     $var wire 1 g Z_flag $end
     $var wire 1 h C_flag $end
     $var wire 1 W Halt $end
     $var wire 1 6 Acc_Read $end
     $var wire 1 5 Acc_Write $end
     $var wire 1 8 Reg_Read $end
     $var wire 3 9 Reg_Read_Addr [2:0] $end
     $var wire 1 7 Reg_Write $end
     $var wire 3 : Reg_Write_Addr [2:0] $end
     $var wire 1 3 Control_Read $end
     $var wire 1 4 Control_Write $end
     $var wire 1 > Io_Read $end
     $var wire 1 ; IR_Write $end
     $var wire 1 < IR_Read $end
     $var wire 1 = MDR_Read $end
     $var wire 3 ? PC_Sel [2:0] $end
     $var wire 1 @ ALU_In_1 $end
     $var wire 1 A ALU_In_2 $end
     $var wire 4 C ALU_Op_Sel [3:0] $end
     $var wire 1 B ALU_Out_Write $end
     $var wire 4 O rom_addr [3:0] $end
     $var wire 26 D CTRL [25:0] $end
     $var wire 3 P write_addr [2:0] $end
     $var wire 3 Q read_addr [2:0] $end
     $var wire 3 H param_2 [2:0] $end
     $var wire 3 I param_1 [2:0] $end
     $var wire 1 J param_2_immd $end
     $var wire 1 K param_1_immd $end
     $var wire 8 L instr [7:0] $end
     $var wire 8 X state [7:0] $end
     $var wire 8 R next_state [7:0] $end
     $scope module rom $end
      $var wire 4 O rom_addr [3:0] $end
      $var wire 3 Q read_addr [2:0] $end
      $var wire 3 P write_addr [2:0] $end
      $var wire 26 D CTRL [25:0] $end
      $var wire 26 S read_reg_addr [25:0] $end
      $var wire 26 T write_reg_addr [25:0] $end
      $var wire 26 l memory[0] [25:0] $end
      $var wire 26 m memory[1] [25:0] $end
      $var wire 26 n memory[2] [25:0] $end
      $var wire 26 o memory[3] [25:0] $end
      $var wire 26 p memory[4] [25:0] $end
      $var wire 26 q memory[5] [25:0] $end
      $var wire 26 r memory[6] [25:0] $end
     $upscope $end
    $upscope $end
    $scope module register $end
     $var wire 32 e DATA_WIDTH [31:0] $end
     $var wire 1 ` clk $end
     $var wire 1 7 write $end
     $var wire 1 8 read $end
     $var wire 1 a reset_n $end
     $var wire 3 9 addr_read [2:0] $end
     $var wire 3 : addr_write [2:0] $end
     $var wire 16 c data_write [15:0] $end
     $var wire 16 c data_read [15:0] $end
     $var wire 96 Y register_file [95:0] $end
     $var wire 16 \ B_reg_debug [15:0] $end
     $var wire 16 ] C_reg_debug [15:0] $end
     $var wire 16 ^ D_reg_debug [15:0] $end
     $var wire 16 _ E_reg_debug [15:0] $end
    $upscope $end
   $upscope $end
  $upscope $end
 $upscope $end
$enddefinitions $end


#0
b0000000000000000 #
b0000000100111000 $
b1100101011111110 %
b0000000101001000 &
b0000000000001001 '
b0000001000100100 (
b0000001000011000 )
b0000000000001010 *
b1111111111111111 +
b1011111011101111 ,
b1101111010101101 -
b0000000000000000 .
b0000000000000000 /
b0000000000000000 0
b0000000000000000 1
b0000000000000000 2
13
04
05
06
07
08
b000 9
b000 :
0;
0<
1=
0>
b001 ?
0@
0A
0B
b0000 C
b00000000001000010010000000 D
b0000000000000000 E
b0000000000000000 F
b0000000000000000 G
b000 H
b000 I
0J
0K
b00000000 L
b0000000000000000 M
b0000000000000000 N
b0000 O
b000 P
b000 Q
b00000001 R
b00000000000000000000000000 S
b00000000000000000000000000 T
b0000000000000000 U
b0000000000000000 V
0W
b00000000 X
b000000000000000000000000000000000000000000000000000000000000000000000000000000000000000000000000 Y
b0000000000000000 \
b0000000000000000 ]
b0000000000000000 ^
b0000000000000000 _
1`
1a
b0000000000000000 b
b0000000000000000 c
b0000000000000001 d
b00000000000000000000000000010000 e
b00000000000000010000000000000000 f
0g
0h
b0000000000000000 i
b0000000000000000 j
b0000000000000000 k
b00000000001000010010000000 l
b00100010000000000000000000 m
b00000000001001000010000000 n
b00000010000000100000000000 o
b00100000000001000000000000 p
b00000010001010000000000000 q
b00000000000000000000000000 r
#10
0`
#20
03
0=
b000 ?
b00000000000000000000000000 D
b0000000000000001 N
b0110 O
b11111111 R
b0000000000000001 U
b00000001 X
b000000000000000000000000000000010000000000000000000000000000000000000000000000000000000000000000 Y
1`
#30
0`
#40
b00000000 R
b11111111 X
1`
#50
0`
0a
#60
b0000000000000000 U
b000000000000000000000000000000000000000000000000000000000000000000000000000000000000000000000000 Y
1`
b0000000000000000 d
#70
0`
#80
1`
#90
0`
#100
13
1=
b001 ?
b00000000001000010010000000 D
b0000000000000000 N
b0000 O
b00000001 R
b00000000 X
1`
1a
b0000000000000001 d
#110
0`
#120
03
0=
b000 ?
b00000000000000000000000000 D
b0000000000000001 N
b0110 O
b11111111 R
b0000000000000001 U
b00000001 X
b000000000000000000000000000000010000000000000000000000000000000000000000000000000000000000000000 Y
1`
#130
0`
#140
b00000000 R
b11111111 X
1`
#150
0`
#160
13
1=
b001 ?
b00000000001000010010000000 D
b0000000100111000 E
b011 I
1J
b00000001 L
b0000000000000001 M
b0000 O
b00000001 R
b00000000 X
1`
b0000000100111000 b
b0000000100111000 c
b0000000000000010 d
#170
0`
#180
1;
0=
b00000000001001000010000000 D
b1100101011111110 F
b0000000000000010 M
b0000000000000010 N
b0010 O
b00000010 R
b0000000000000010 U
b00000001 X
b000000000000000000000000000000100000000000000000000000000000000000000000000000000000000000000000 Y
1`
b1100101011111110 b
b1100101011111110 c
b0000000000000011 d
#190
0`
#200
03
17
b011 :
0;
1<
b000 ?
b00000010110000100000000000 D
b0000000000000000 M
b0000000000000011 N
b0011 O
b011 P
b11111111 R
b00000000110000000000000000 T
b0000000000000011 U
b00000010 X
b000000000000000000000000000000110000000000000000000000000000000000000000000000000000000000000000 Y
1`
b0000000000000000 b
#210
0`
#220
07
b000 :
0<
b00000000000000000000000000 D
b0110 O
b000 P
b00000000 R
b00000000000000000000000000 T
b11111111 X
b000000000000000000000000000000110000000000000000110010101111111000000000000000000000000000000000 Y
b1100101011111110 ^
1`
b0000000000000000 c
#230
0`
#240
13
1=
b001 ?
b00000000001000010010000000 D
b0000000101001000 E
b100 I
b0000000000000011 M
b0000 O
b00000001 R
b00000000 X
1`
b0000000101001000 b
b0000000101001000 c
b0000000000000100 d
#250
0`
#260
1;
0=
b00000000001001000010000000 D
b0000000000001001 F
b0000000000000100 M
b0000000000000100 N
b0010 O
b00000010 R
b0000000000000100 U
b00000001 X
b000000000000000000000000000001000000000000000000110010101111111000000000000000000000000000000000 Y
1`
b0000000000001001 b
b0000000000001001 c
b0000000000000101 d
#270
0`
#280
03
17
b100 :
0;
1<
b000 ?
b00000011000000100000000000 D
b0000000000000000 M
b0000000000000101 N
b0011 O
b100 P
b11111111 R
b00000001000000000000000000 T
b0000000000000101 U
b00000010 X
b000000000000000000000000000001010000000000000000110010101111111000000000000000000000000000000000 Y
1`
b0000000000000000 b
#290
0`
#300
07
b000 :
0<
b00000000000000000000000000 D
b0110 O
b000 P
b00000000 R
b00000000000000000000000000 T
b11111111 X
b000000000000000000000000000001010000000000001001110010101111111000000000000000000000000000000000 Y
b0000000000001001 _
1`
b0000000000000000 c
#310
0`
#320
13
1=
b001 ?
b00000000001000010010000000 D
b0000001000100100 E
b100 H
b010 I
0J
b00000010 L
b0000000000000101 M
b0000 O
b00000001 R
b00000000 X
1`
b0000001000100100 b
b0000001000100100 c
b0000000000000110 d
#330
0`
#340
03
18
b100 9
1;
0=
b000 ?
b00110000000001000000000000 D
b0000000000000000 M
b0000000000000110 N
b0100 O
b100 Q
b00000010 R
b00010000000000000000000000 S
b0000000000000110 U
b00000001 X
b000000000000000000000000000001100000000000001001110010101111111000000000000000000000000000000000 Y
1`
b0000000000000000 b
b0000000000001001 c
#350
0`
#360
13
17
08
b000 9
b010 :
0;
1>
b00000010101010000000000000 D
b0000000000001001 M
b0000000000001001 N
b0101 O
b010 P
b000 Q
b11111111 R
b00000000000000000000000000 S
b00000000100000000000000000 T
b00000010 X
1`
b1011111011101111 b
b1011111011101111 c
#370
0`
#380
03
07
b000 :
0>
b00000000000000000000000000 D
b0000000000000000 M
b0110 O
b000 P
b00000000 R
b00000000000000000000000000 T
b11111111 X
b000000000000000000000000000001100000000000001001110010101111111010111110111011110000000000000000 Y
b1011111011101111 ]
1`
b0000000000000000 b
b0000000000000000 c
#390
0`
#400
13
1=
b001 ?
b00000000001000010010000000 D
b0000001000011000 E
b000 H
b001 I
1J
b0000000000000110 M
b0000000000000110 N
b0000 O
b00000001 R
b00000000 X
1`
b0000001000011000 b
b0000001000011000 c
b0000000000000111 d
#410
0`
#420
1;
0=
b00000000001001000010000000 D
b0000000000001010 F
b0000000000000111 M
b0000000000000111 N
b0010 O
b00000010 R
b0000000000000111 U
b00000001 X
b000000000000000000000000000001110000000000001001110010101111111010111110111011110000000000000000 Y
1`
b0000000000001010 b
b0000000000001010 c
b0000000000001000 d
#430
0`
#440
17
b001 :
0;
1>
b000 ?
b00000010011010000000000000 D
b0000000000001010 M
b0000000000001010 N
b0101 O
b001 P
b11111111 R
b00000000010000000000000000 T
b0000000000001000 U
b00000010 X
b000000000000000000000000000010000000000000001001110010101111111010111110111011110000000000000000 Y
1`
b1101111010101101 b
b1101111010101101 c
#450
0`
#460
03
07
b000 :
0>
b00000000000000000000000000 D
b0000000000000000 M
b0110 O
b000 P
b00000000 R
b00000000000000000000000000 T
b11111111 X
b000000000000000000000000000010000000000000001001110010101111111010111110111011111101111010101101 Y
b1101111010101101 \
1`
b0000000000000000 b
b0000000000000000 c
#470
0`
#480
13
1=
b001 ?
b00000000001000010010000000 D
b1111111111111111 E
b111 H
b111 I
1K
b11111111 L
b0000000000001000 M
b0000000000001000 N
b0000 O
b00000001 R
b00000000 X
1`
b1111111111111111 b
b1111111111111111 c
b0000000000001001 d
#490
0`
#500
03
0=
b000 ?
b00000000000000000000000000 D
b0000000000000000 M
b0000000000001001 N
b0110 O
b11111111 R
b0000000000001001 U
b00000001 X
b000000000000000000000000000010010000000000001001110010101111111010111110111011111101111010101101 Y
1`
b0000000000000000 b
b0000000000000000 c
#510
0`
#520
b00000000 R
b11111111 X
1`
#530
0`
#540
1W
b00000000 X
1`
