hardware/opcode.sv
`define NOP 8'b0000_0000
`define HLT 8'b1111_1111

`define MOV 8'b0000_0001
`define LDA 8'b0000_0010
`define STA 8'b0000_0011

`define ADD 8'b0000_0100
`define SUB 8'b0000_0101
`define MUL 8'b0000_0110
`define DIV 8'b0000_0111

`define AND 8'b0000_1000
`define OR 8'b0000_1001
`define XOR 8'b0000_1010
`define NOT 8'b0000_1011
`define RR 8'b0000_1100

`define PUSH 8'b0000_1101
`define POP 8'b0000_1110

`define JUMP 8'b1000_0000
`define CALL 8'b1010_0000
`define RET 8'b1011_0000

`define NO_REG 3'b000
`define B_REG 3'b001
`define C_REG 3'b010
`define D_REG 3'b001
`define E_REG 3'b100
`define PC_REG 3'b101
`define SP_REG 3'b110
`define A_REG 3'b111

`define NO_OP 4'b0000
`define ADD_OP 4'b0001
`define SUB_OP 4'b0010
`define MUL_OP 4'b0011
`define DIV_OP 4'b0100
`define AND_OP 4'b1000
`define OR_OP 4'b1001
`define XOR_OP 4'b1010
`define NOT_OP 4'b1011
`define RRS_OP 4'b1100
`define RRC_OP 4'b1101
`define LLS_OP 4'b1110
`define LLC_OP 4'b1111

hardware/Control.sv
`include "opcode.sv"

`timescale 1ns / 100ps
`define ROM_ADDR_SIZE 4
`define ROM_DATA_SIZE 26
`define ROM_NUM_INST_SIZE 5
`define ROM_NOTHING `ROM_NUM_INST_SIZE - 1
`define RESET 255
`define STATE_END 0

module ROM (
    input  logic [`ROM_ADDR_SIZE - 1 : 0] rom_addr,
    input  logic [                 2 : 0] read_addr,
    input  logic [                 2 : 0] write_addr,
    output logic [`ROM_DATA_SIZE - 1 : 0] CTRL
);

    logic [`ROM_DATA_SIZE - 1 : 0] read_reg_addr, write_reg_addr;

    // always_comb begin
    //     read_reg_addr  = (read_addr != 3'h0) ? (`ROM_NOTHING - 3 - read_addr) : `ROM_NOTHING;
    //     write_reg_addr = (write_addr != 3'h0) ? (`ROM_NOTHING - write_addr) : `ROM_NOTHING;
    // end

    always_comb begin
        read_reg_addr  = (read_addr == 3'b111) ? (1'b1 << 25) : (read_addr << 20);
        write_reg_addr = (write_addr == 3'b111) ? (1'b1 << 24) : (write_addr << 16);
    end

    // localparam logic [`ROM_DATA_SIZE * (`ROM_NUM_INST_SIZE + 1) - 1:0] memory = {
    localparam logic [`ROM_DATA_SIZE - 1 : 0] memory[`ROM_NUM_INST_SIZE] = {
        /*
         * Acc_Read, Acc_Write,
         * Reg_Read, Reg_Read_Addr[2:0], Reg_Write, Reg_Write_Addr[2:0],
         * Control_Read, Control_Write, Io_Read, IR_Write, IR_Read, MDR_Read, PC_Sel[2:0],
         * ALU_In_1, ALU_In_2, ALU_Op_Sel[3:0], ALU_Out_Write
         */

        // Fetch
        `ROM_DATA_SIZE'b0_0_0_000_0_000_1_0_0_0_0_1_001_0_0_0000_0,  // MDR <- [PC]

        // Decode & Execute
        `ROM_DATA_SIZE'b0_0_1_000_1_000_0_0_0_0_0_0_000_0_0_0000_0,  // Rd <- Rs
        `ROM_DATA_SIZE'b0_0_0_000_0_000_1_0_0_1_0_0_001_0_0_0000_0,  // IR <- data
        `ROM_DATA_SIZE'b0_0_0_000_1_000_0_0_0_0_1_0_000_0_0_0000_0,  // Rd <- IR

        /* Read Register select */
        // `ROM_DATA_SIZE'b0_0_0_100_0_000_0_0_0_0_0_0_000_0_0_0000_0,  // E
        // `ROM_DATA_SIZE'b0_0_0_011_0_000_0_0_0_0_0_0_000_0_0_0000_0,  // D
        // `ROM_DATA_SIZE'b0_0_0_010_0_000_0_0_0_0_0_0_000_0_0_0000_0,  // C
        // `ROM_DATA_SIZE'b0_0_0_001_0_000_0_0_0_0_0_0_000_0_0_0000_0,  // B

        // /* Write Register select */
        // `ROM_DATA_SIZE'b0_0_0_000_0_100_0_0_0_0_0_0_000_0_0_0000_0,  // E
        // `ROM_DATA_SIZE'b0_0_0_000_0_011_0_0_0_0_0_0_000_0_0_0000_0,  // D
        // `ROM_DATA_SIZE'b0_0_0_000_0_010_0_0_0_0_0_0_000_0_0_0000_0,  // C
        // `ROM_DATA_SIZE'b0_0_0_000_0_001_0_0_0_0_0_0_000_0_0_0000_0,  // B

        // END
        `ROM_DATA_SIZE'b0_000_0_000_0_0_0_0_0_0_000_0_0_0000_0  // Nothing
    };

    assign CTRL = memory[rom_addr] | read_reg_addr | write_reg_addr;
    // assign CTRL     = memory[ `ROM_DATA_SIZE * rom_addr +: `ROM_DATA_SIZE ] | memory[ `ROM_DATA_SIZE * read_reg_addr +: `ROM_DATA_SIZE ] | memory[ `ROM_DATA_SIZE * write_reg_addr +: `ROM_DATA_SIZE ];
endmodule

module Control #(
    parameter unsigned DATA_WIDTH = 16
) (
    input logic                      reset_n,
    input logic                      clk,
    input logic [DATA_WIDTH - 1 : 0] MDR,
    input logic                      Z_flag,
    input logic                      C_flag,

    output logic         Acc_Read,
    output logic         Acc_Write,
    output logic         Reg_Read,
    output logic [2 : 0] Reg_Read_Addr,
    output logic         Reg_Write,
    output logic [2 : 0] Reg_Write_Addr,
    output logic         Control_Read,
    output logic         Control_Write,
    output logic         Io_Read,
    output logic         IR_Write,
    output logic         IR_Read,
    output logic         MDR_Read,
    output logic [2 : 0] PC_Sel,
    output logic         ALU_In_1,
    output logic         ALU_In_2,
    output logic [3 : 0] ALU_Op_Sel,
    output logic         ALU_Out_Write
);

    logic [`ROM_ADDR_SIZE - 1 : 0] rom_addr;
    logic [`ROM_DATA_SIZE - 1 : 0] CTRL;

    logic [2 : 0] write_addr, read_addr, param_2, param_1;
    logic param_2_immd, param_1_immd;
    logic [7 : 0] instr;

    logic [7 : 0] state, next_state;

    ROM rom (
        .rom_addr  (rom_addr),
        .read_addr (read_addr),
        .write_addr(write_addr),
        .CTRL      (CTRL)
    );

    assign {instr, param_1_immd, param_1, param_2_immd, param_2} = MDR;

    assign {Acc_Read, Acc_Write,
            Reg_Read, Reg_Read_Addr, Reg_Write, Reg_Write_Addr,
            Control_Read, Control_Write, Io_Read, IR_Write, IR_Read, MDR_Read,
            PC_Sel,
            ALU_In_1, ALU_In_2, ALU_Op_Sel, ALU_Out_Write} = CTRL;

    always_ff @(posedge clk) begin
        if (!reset_n) state <= `RESET;
        else state <= next_state;
    end

    always_comb begin
        case (state)
            // Fetch
            0: begin
                rom_addr   = 0;
                write_addr = 0;
                read_addr  = 0;
                next_state = 1;
            end

            // Decode & Execute
            1: begin
                case (instr)
                    `NOP: begin
                        rom_addr   = `ROM_NOTHING;
                        write_addr = 0;
                        read_addr  = 0;
                        next_state = `STATE_END;
                    end
                    `MOV: begin
                        if (param_2_immd == 1'b1) begin
                            rom_addr   = 2;
                            write_addr = 0;
                            read_addr  = 0;
                            next_state = 2;
                        end else begin
                            rom_addr   = 1;
                            write_addr = param_1;
                            read_addr  = param_2;
                            next_state = `STATE_END;
                        end
                    end

                    default: begin
                        rom_addr   = `ROM_NOTHING;
                        write_addr = 0;
                        read_addr  = 0;
                        next_state = `STATE_END;
                    end
                endcase
            end
            2: begin
                case (instr)

                    `MOV: begin
                        rom_addr   = 3;
                        write_addr = param_1;
                        read_addr  = 0;
                        next_state = `STATE_END;
                    end

                    default: begin
                        rom_addr   = `ROM_NOTHING;
                        write_addr = 0;
                        read_addr  = 0;
                        next_state = `STATE_END;
                    end
                endcase
            end

            // End / Reset Cycle
            `RESET: begin
                rom_addr   = `ROM_NOTHING;
                write_addr = 0;
                read_addr  = 0;
                next_state = 0;
            end

            default: begin
            end
        endcase
    end

endmodule

hardware/Register.sv
`timescale 1ns / 100ps

typedef struct packed {
    logic [16 - 1 : 0] SP;
    logic [16 - 1 : 0] PC;
    logic [16 - 1 : 0] E_reg;
    logic [16 - 1 : 0] D_reg;
    logic [16 - 1 : 0] C_reg;
    logic [16 - 1 : 0] B_reg;
} register_def_t;

typedef union packed {
    register_def_t    reg_list;
    logic   [ 6 * 16 - 1 : 0 ] reg_array;
} register_file_t;

module Register #(
    parameter unsigned DATA_WIDTH = 16
) (
    input                             clk,
    input  logic                      write,
    input  logic                      read,
    input  logic                      reset_n,
    input  logic [             2 : 0] addr_read,
    input  logic [             2 : 0] addr_write,
    input  logic [DATA_WIDTH - 1 : 0] data_write,
    output logic [DATA_WIDTH - 1 : 0] data_read
);

    // logic [4 * DATA_WIDTH - 1 : 0] register;
    register_file_t register_file;

    // debug
    logic [16 - 1 : 0] B_reg_debug;
    logic [16 - 1 : 0] C_reg_debug;
    logic [16 - 1 : 0] D_reg_debug;
    logic [16 - 1 : 0] E_reg_debug;
    // logic [4 * 16 - 1 : 0] reg_array_debug;

    assign B_reg_debug = register_file.reg_list.B_reg;
    assign C_reg_debug = register_file.reg_list.C_reg;
    assign D_reg_debug = register_file.reg_list.D_reg;
    assign E_reg_debug = register_file.reg_list.E_reg;
    // assign reg_array_debug = register.reg_array;

    always @(posedge clk) begin
        if (!reset_n) register_file <= 'b0;
        else if (write && (addr_write != 'b0))
            register_file[DATA_WIDTH*(addr_write-1)+:DATA_WIDTH] <= data_write;
    end

    assign data_read = (read && (addr_read != 'b0))
                        ? register_file[DATA_WIDTH * ( addr_read - 1 ) +: DATA_WIDTH]
                        : {DATA_WIDTH {1'hz}};

endmodule

hardware/Processor.sv
`timescale 1ns / 100ps

module Processor #(
    parameter unsigned ADDR_WIDTH = 16,
    parameter unsigned DATA_WIDTH = 16
) (
    output logic [ADDR_WIDTH - 1 : 0] address,
    inout  logic [DATA_WIDTH - 1 : 0] data,
    output bit                        read_mem,
    output bit                        write_mem,
    input  bit                        reset_n,
    input  logic                      clk
);

    ////////////////////////  Declaration & Inittialization  ///////////////////////////////
    // Registers & flags
    reg [ADDR_WIDTH - 1 : 0] PC_debug, SP_debug;
    reg [DATA_WIDTH - 1 : 0] MDR, IR, Acc;
    logic Z_flag, C_flag;

    let PC = register.register_file.reg_list.PC;
    let SP = register.register_file.reg_list.SP;
    assign PC_debug = PC;
    assign SP_debug = SP;

    // control signals
    logic Acc_Write, Acc_Read, Reg_Write, Reg_Read;
    logic [2 : 0] Reg_Read_Addr, Reg_Write_Addr;
    logic Control_Read, IR_Write, IR_Read, MDR_Read, Io_Read, Control_Write;
    wire [2 : 0] PC_Sel;
    logic ALU_In_1, ALU_In_2, ALU_Out_Write;
    logic [3 : 0] ALU_Op_Sel;

    // interconnect wires & reg
    wire [DATA_WIDTH - 1 : 0] internal_databus;
    logic [ADDR_WIDTH - 1 : 0] next_pc;
    logic [DATA_WIDTH - 1 : 0] ALU_Src_A, ALU_Src_B, ALU_out;

    // ALU
    // Alu alu (
    //     .A_reg     (ALU_Src_A),
    //     .B_reg     (ALU_Src_B),
    //     .op_select (ALU_Op_Sel),
    //     .ALU_output(ALU_out),
    //     .Z_flag    (Z_flag),
    //     .C_flag    (C_flag)
    // );

    // Register File
    Register register (
        .write     (Reg_Write),
        .read      (Reg_Read),
        .reset_n   (reset_n),
        .clk       (clk),
        .data_read (internal_databus),
        .data_write(internal_databus),
        .addr_read (Reg_Read_Addr),
        .addr_write(Reg_Write_Addr)
    );

    // Control Unit
    Control control (
        .reset_n       (reset_n),
        .clk           (clk),
        .MDR           (MDR),
        .Acc_Read      (Acc_Read),
        .Acc_Write     (Acc_Write),
        .Reg_Write     (Reg_Write),
        .Reg_Read      (Reg_Read),
        .Control_Read  (Control_Read),
        .Control_Write (Control_Write),
        .Io_Read       (Io_Read),
        .IR_Write      (IR_Write),
        .IR_Read       (IR_Read),
        .MDR_Read      (MDR_Read),
        .PC_Sel        (PC_Sel),
        .Z_flag        (Z_flag),
        .C_flag        (C_flag),
        .ALU_In_1      (ALU_In_1),
        .ALU_In_2      (ALU_In_2),
        .ALU_Op_Sel    (ALU_Op_Sel),
        .ALU_Out_Write (ALU_Out_Write),
        .Reg_Read_Addr (Reg_Read_Addr),
        .Reg_Write_Addr(Reg_Write_Addr)
    );

    ////////////////////////////////////////////////////////////////////////////////////////

    ////////////////////////  Memory Access  ////////////////////////////

    assign read_mem  = Control_Read ? 1 : 0;
    assign write_mem = Control_Write ? 1 : 0;
    always_latch begin
        if (MDR_Read) MDR = internal_databus;
        if (IR_Write) IR = internal_databus;
        if (Acc_Write && Reg_Write) Acc = internal_databus;
    end

    assign internal_databus = read_mem ? data
                                : (ALU_Out_Write ? ALU_out
                                    : (IR_Read ? IR
                                        : ((Acc_Read && Reg_Read) ? Acc
                                            : {DATA_WIDTH {1'hz}})));

    assign address = Control_Read ? (Io_Read ? IR : PC) : (Control_Write ? IR : {ADDR_WIDTH{1'hz}});
    assign data = write_mem ? internal_databus : {DATA_WIDTH{1'hz}};

    //////////////////////////////////////////////////////////////////////

    ////////////////////////  ALU  ////////////////////////////

    // always_comb begin
    //     case (ALU_In_1)
    //         1: ALU_Src_A = internal_databus;
    //         default: begin
    //             ALU_Src_A = {DATA_WIDTH{1'b0}};
    //         end
    //     endcase
    //     case (ALU_In_2)
    //         0: ALU_Src_B = internal_databus;
    //         1: ALU_Src_B = IR;
    //         default: begin
    //             ALU_Src_B = {DATA_WIDTH{1'b0}};
    //         end
    //     endcase
    // end

    ///////////////////////////////////////////////////////////

    ////////////////////////  CPU reset Program Counter ////////////////////////////

    always_comb begin
        case (PC_Sel)
            0:       next_pc = PC + {ADDR_WIDTH{1'b0}};
            1:       next_pc = PC + 1'b1;
            2:       next_pc = Z_flag ? IR : PC + 1'b1;
            3:       next_pc = (!Z_flag) ? IR : PC + 1'b1;
            4:       next_pc = (C_flag) ? IR : PC + 1'b1;
            5:       next_pc = (!C_flag) ? IR : PC + 1'b1;
            default: next_pc = PC + {ADDR_WIDTH{1'b0}};
        endcase
    end

    always_ff @(posedge clk) begin
        if (!reset_n) PC <= {ADDR_WIDTH{1'b0}};
        else PC <= next_pc;
    end

    //////////////////////////////////////////////////////////////////////

endmodule

hardware/Memory.sv
`timescale 1ns / 100ps

module Memory #(
    parameter unsigned ADDR_WIDTH = 16,
    parameter unsigned DATA_WIDTH = 16,
    parameter unsigned DEPTH = 2 ** ADDR_WIDTH
) (
    input logic                      clk,
    input bit                        write,
    input bit                        read,
    input logic [ADDR_WIDTH - 1 : 0] addr,
    inout logic [DATA_WIDTH - 1 : 0] data
);

    logic [DATA_WIDTH - 1 : 0] read_addr;
    logic [DATA_WIDTH - 1 : 0] mem[DEPTH];

    always_comb begin
        if (write) mem[addr] = data;
        if (read) read_addr = addr;
    end

    assign data = read ? mem[read_addr] : {DATA_WIDTH{1'hz}};
endmodule

hardware/test_benches/Processor_tb.sv
`timescale 1ns / 100ps

module Processor_tb;
    parameter unsigned ADDR_WIDTH = 16;
    parameter unsigned DATA_WIDTH = 16;


    logic clk, read, write, reset_n;
    logic [ADDR_WIDTH-1:0] addr;
    wire  [DATA_WIDTH-1:0] data;

    Memory memory (
        .write(write),
        .read (read),
        .clk  (clk),
        .addr (addr),
        .data (data)
    );

    Processor u0 (
        .address  (addr),
        .data     (data),
        .read_mem (read),
        .write_mem(write),
        .clk      (clk),
        .reset_n  (reset_n)
    );



    always #1 clk = ~clk;

    initial begin
        clk     = 1;
        reset_n = 1;
        $readmemh("memory.hex", memory.mem, 0, 6);

        #5 reset_n = 0;
        #5 reset_n = 1;
        #30 $finish;
    end
    initial begin
        $dumpfile("waveform.vcd");
        $dumpvars;
    end

endmodule

hardware/test_benches/waveform.vcd
$version Generated by VerilatedVcd $end
$timescale 100ps $end
 $scope module TOP $end
  $scope module Processor_tb $end
   $var wire 32 T ADDR_WIDTH [31:0] $end
   $var wire 32 T DATA_WIDTH [31:0] $end
   $var wire 1 O clk $end
   $var wire 1 # read $end
   $var wire 1 $ write $end
   $var wire 1 P reset_n $end
   $var wire 16 = addr [15:0] $end
   $var wire 16 Q data [15:0] $end
   $scope module memory $end
    $var wire 32 T ADDR_WIDTH [31:0] $end
    $var wire 32 T DATA_WIDTH [31:0] $end
    $var wire 32 U DEPTH [31:0] $end
    $var wire 1 O clk $end
    $var wire 1 $ write $end
    $var wire 1 # read $end
    $var wire 16 = addr [15:0] $end
    $var wire 16 Q data [15:0] $end
    $var wire 16 > read_addr [15:0] $end
   $upscope $end
   $scope module u0 $end
    $var wire 32 T ADDR_WIDTH [31:0] $end
    $var wire 32 T DATA_WIDTH [31:0] $end
    $var wire 16 = address [15:0] $end
    $var wire 16 Q data [15:0] $end
    $var wire 1 # read_mem $end
    $var wire 1 $ write_mem $end
    $var wire 1 P reset_n $end
    $var wire 1 O clk $end
    $var wire 16 E PC_debug [15:0] $end
    $var wire 16 F SP_debug [15:0] $end
    $var wire 16 5 MDR [15:0] $end
    $var wire 16 6 IR [15:0] $end
    $var wire 16 7 Acc [15:0] $end
    $var wire 1 V Z_flag $end
    $var wire 1 W C_flag $end
    $var wire 1 % Acc_Write $end
    $var wire 1 & Acc_Read $end
    $var wire 1 ' Reg_Write $end
    $var wire 1 ( Reg_Read $end
    $var wire 3 ) Reg_Read_Addr [2:0] $end
    $var wire 3 * Reg_Write_Addr [2:0] $end
    $var wire 1 # Control_Read $end
    $var wire 1 + IR_Write $end
    $var wire 1 , IR_Read $end
    $var wire 1 - MDR_Read $end
    $var wire 1 . Io_Read $end
    $var wire 1 $ Control_Write $end
    $var wire 3 / PC_Sel [2:0] $end
    $var wire 1 0 ALU_In_1 $end
    $var wire 1 1 ALU_In_2 $end
    $var wire 1 2 ALU_Out_Write $end
    $var wire 4 3 ALU_Op_Sel [3:0] $end
    $var wire 16 R internal_databus [15:0] $end
    $var wire 16 S next_pc [15:0] $end
    $var wire 16 X ALU_Src_A [15:0] $end
    $var wire 16 Y ALU_Src_B [15:0] $end
    $var wire 16 Z ALU_out [15:0] $end
    $scope module control $end
     $var wire 32 T DATA_WIDTH [31:0] $end
     $var wire 1 P reset_n $end
     $var wire 1 O clk $end
     $var wire 16 5 MDR [15:0] $end
     $var wire 1 V Z_flag $end
     $var wire 1 W C_flag $end
     $var wire 1 & Acc_Read $end
     $var wire 1 % Acc_Write $end
     $var wire 1 ( Reg_Read $end
     $var wire 3 ) Reg_Read_Addr [2:0] $end
     $var wire 1 ' Reg_Write $end
     $var wire 3 * Reg_Write_Addr [2:0] $end
     $var wire 1 # Control_Read $end
     $var wire 1 $ Control_Write $end
     $var wire 1 . Io_Read $end
     $var wire 1 + IR_Write $end
     $var wire 1 , IR_Read $end
     $var wire 1 - MDR_Read $end
     $var wire 3 / PC_Sel [2:0] $end
     $var wire 1 0 ALU_In_1 $end
     $var wire 1 1 ALU_In_2 $end
     $var wire 4 3 ALU_Op_Sel [3:0] $end
     $var wire 1 2 ALU_Out_Write $end
     $var wire 4 ? rom_addr [3:0] $end
     $var wire 26 4 CTRL [25:0] $end
     $var wire 3 @ write_addr [2:0] $end
     $var wire 3 A read_addr [2:0] $end
     $var wire 3 8 param_2 [2:0] $end
     $var wire 3 9 param_1 [2:0] $end
     $var wire 1 : param_2_immd $end
     $var wire 1 ; param_1_immd $end
     $var wire 8 < instr [7:0] $end
     $var wire 8 G state [7:0] $end
     $var wire 8 B next_state [7:0] $end
     $scope module rom $end
      $var wire 4 ? rom_addr [3:0] $end
      $var wire 3 A read_addr [2:0] $end
      $var wire 3 @ write_addr [2:0] $end
      $var wire 26 4 CTRL [25:0] $end
      $var wire 26 C read_reg_addr [25:0] $end
      $var wire 26 D write_reg_addr [25:0] $end
      $var wire 26 [ memory[0] [25:0] $end
      $var wire 26 \ memory[1] [25:0] $end
      $var wire 26 ] memory[2] [25:0] $end
      $var wire 26 ^ memory[3] [25:0] $end
      $var wire 26 _ memory[4] [25:0] $end
     $upscope $end
    $upscope $end
    $scope module register $end
     $var wire 32 T DATA_WIDTH [31:0] $end
     $var wire 1 O clk $end
     $var wire 1 ' write $end
     $var wire 1 ( read $end
     $var wire 1 P reset_n $end
     $var wire 3 ) addr_read [2:0] $end
     $var wire 3 * addr_write [2:0] $end
     $var wire 16 R data_write [15:0] $end
     $var wire 16 R data_read [15:0] $end
     $var wire 96 H register_file [95:0] $end
     $var wire 16 K B_reg_debug [15:0] $end
     $var wire 16 L C_reg_debug [15:0] $end
     $var wire 16 M D_reg_debug [15:0] $end
     $var wire 16 N E_reg_debug [15:0] $end
    $upscope $end
   $upscope $end
  $upscope $end
 $upscope $end
$enddefinitions $end


#0
1#
0$
0%
0&
0'
0(
b000 )
b000 *
0+
0,
1-
0.
b001 /
00
01
02
b0000 3
b00000000001000010010000000 4
b0000000000000000 5
b0000000000000000 6
b0000000000000000 7
b000 8
b000 9
0:
0;
b00000000 <
b0000000000000000 =
b0000000000000000 >
b0000 ?
b000 @
b000 A
b00000001 B
b00000000000000000000000000 C
b00000000000000000000000000 D
b0000000000000000 E
b0000000000000000 F
b00000000 G
b000000000000000000000000000000000000000000000000000000000000000000000000000000000000000000000000 H
b0000000000000000 K
b0000000000000000 L
b0000000000000000 M
b0000000000000000 N
1O
1P
b0000000000000000 Q
b0000000000000000 R
b0000000000000001 S
b00000000000000000000000000010000 T
b00000000000000010000000000000000 U
0V
0W
b0000000000000000 X
b0000000000000000 Y
b0000000000000000 Z
b00000000001000010010000000 [
b00100010000000000000000000 \
b00000000001001000010000000 ]
b00000010000000100000000000 ^
b00000000000000000000000000 _
#10
0O
#20
0#
0-
b000 /
b00000000000000000000000000 4
b0000000000000001 >
b0100 ?
b00000000 B
b0000000000000001 E
b00000001 G
b000000000000000000000000000000010000000000000000000000000000000000000000000000000000000000000000 H
1O
#30
0O
#40
1#
1-
b001 /
b00000000001000010010000000 4
b0000000100101000 5
b010 9
1:
b00000001 <
b0000000000000001 =
b0000 ?
b00000001 B
b00000000 G
1O
b0000000100101000 Q
b0000000100101000 R
b0000000000000010 S
#50
0O
0P
#60
0#
0-
b000 /
b00000000000000000000000000 4
b0000000000000000 =
b0000000000000000 >
b0100 ?
b00000000 B
b0000000000000000 E
b11111111 G
b000000000000000000000000000000000000000000000000000000000000000000000000000000000000000000000000 H
1O
b0000000000000000 Q
b0000000000000000 R
b0000000000000000 S
#70
0O
#80
1O
#90
0O
#100
1#
1-
b001 /
b00000000001000010010000000 4
b0000000000000000 5
b000 9
0:
b00000000 <
b0000 ?
b00000001 B
b00000000 G
1O
1P
b0000000000000001 S
#110
0O
#120
0#
0-
b000 /
b00000000000000000000000000 4
b0000000000000001 >
b0100 ?
b00000000 B
b0000000000000001 E
b00000001 G
b000000000000000000000000000000010000000000000000000000000000000000000000000000000000000000000000 H
1O
#130
0O
#140
1#
1-
b001 /
b00000000001000010010000000 4
b0000000100101000 5
b010 9
1:
b00000001 <
b0000000000000001 =
b0000 ?
b00000001 B
b00000000 G
1O
b0000000100101000 Q
b0000000100101000 R
b0000000000000010 S
#150
0O
#160
1+
0-
b00000000001001000010000000 4
b1100101011111110 6
b0000000000000010 =
b0000000000000010 >
b0010 ?
b00000010 B
b0000000000000010 E
b00000001 G
b000000000000000000000000000000100000000000000000000000000000000000000000000000000000000000000000 H
1O
b1100101011111110 Q
b1100101011111110 R
b0000000000000011 S
#170
0O
#180
0#
1'
b010 *
0+
1,
b000 /
b00000010100000100000000000 4
b0000000000000000 =
b0000000000000011 >
b0011 ?
b010 @
b00000000 B
b00000000100000000000000000 D
b0000000000000011 E
b00000010 G
b000000000000000000000000000000110000000000000000000000000000000000000000000000000000000000000000 H
1O
b0000000000000000 Q
#190
0O
#200
1#
0'
b000 *
0,
1-
b001 /
b00000000001000010010000000 4
b0000000100010010 5
b010 8
b001 9
0:
b0000000000000011 =
b0000 ?
b000 @
b00000001 B
b00000000000000000000000000 D
b00000000 G
b000000000000000000000000000000110000000000000000000000000000000011001010111111100000000000000000 H
b1100101011111110 L
1O
b0000000100010010 Q
b0000000100010010 R
b0000000000000100 S
#210
0O
#220
0#
1'
1(
b010 )
b001 *
0-
b000 /
b00101010010000000000000000 4
b0000000000000000 =
b0000000000000100 >
b0001 ?
b001 @
b010 A
b00000000 B
b00001000000000000000000000 C
b00000000010000000000000000 D
b0000000000000100 E
b00000001 G
b000000000000000000000000000001000000000000000000000000000000000011001010111111100000000000000000 H
1O
b0000000000000000 Q
b1100101011111110 R
#230
0O
#240
1#
0'
0(
b000 )
b000 *
1-
b001 /
b00000000001000010010000000 4
b0000000101110001 5
b001 8
b111 9
b0000000000000100 =
b0000 ?
b000 @
b000 A
b00000001 B
b00000000000000000000000000 C
b00000000000000000000000000 D
b00000000 G
b000000000000000000000000000001000000000000000000000000000000000011001010111111101100101011111110 H
b1100101011111110 K
1O
b0000000101110001 Q
b0000000101110001 R
b0000000000000101 S
#250
0O
#260
0#
1%
1'
1(
b001 )
0-
b000 /
b01100110000000000000000000 4
b1100101011111110 7
b0000000000000000 =
b0000000000000101 >
b0001 ?
b111 @
b001 A
b00000000 B
b00000100000000000000000000 C
b01000000000000000000000000 D
b0000000000000101 E
b00000001 G
b000000000000000000000000000001010000000000000000000000000000000011001010111111101100101011111110 H
1O
b0000000000000000 Q
b1100101011111110 R
#270
0O
#280
1#
0%
0'
0(
b000 )
1-
b001 /
b00000000001000010010000000 4
b0000000101000111 5
b111 8
b100 9
b0000000000000101 =
b0000 ?
b000 @
b000 A
b00000001 B
b00000000000000000000000000 C
b00000000000000000000000000 D
b00000000 G
1O
b0000000101000111 Q
b0000000101000111 R
b0000000000000110 S
#290
0O
#300
0#
1&
1'
1(
b100 *
0-
b000 /
b10100011000000000000000000 4
b0000000000000000 =
b0000000000000110 >
b0001 ?
b100 @
b111 A
b00000000 B
b10000000000000000000000000 C
b00000001000000000000000000 D
b0000000000000110 E
b00000001 G
b000000000000000000000000000001100000000000000000000000000000000011001010111111101100101011111110 H
1O
b0000000000000000 Q
b1100101011111110 R
#310
0O
#320
1#
0&
0'
0(
b000 *
1-
b001 /
b00000000001000010010000000 4
b1111111111111111 5
b111 9
1:
1;
b11111111 <
b0000000000000110 =
b0000 ?
b000 @
b000 A
b00000001 B
b00000000000000000000000000 C
b00000000000000000000000000 D
b00000000 G
b000000000000000000000000000001101100101011111110000000000000000011001010111111101100101011111110 H
b1100101011111110 N
1O
b1111111111111111 Q
b1111111111111111 R
b0000000000000111 S
#330
0O
#340
0#
0-
b000 /
b00000000000000000000000000 4
b0000000000000000 =
b0000000000000111 >
b0100 ?
b00000000 B
b0000000000000111 E
b00000001 G
b000000000000000000000000000001111100101011111110000000000000000011001010111111101100101011111110 H
1O
b0000000000000000 Q
b0000000000000000 R
#350
0O
#360
1#
1-
b001 /
b00000000001000010010000000 4
b0000000000000000 5
b000 8
b000 9
0:
0;
b00000000 <
b0000000000000111 =
b0000 ?
b00000001 B
b00000000 G
1O
b0000000000001000 S
#370
0O
#380
0#
0-
b000 /
b00000000000000000000000000 4
b0000000000000000 =
b0000000000001000 >
b0100 ?
b00000000 B
b0000000000001000 E
b00000001 G
b000000000000000000000000000010001100101011111110000000000000000011001010111111101100101011111110 H
1O
#390
0O
#400
1#
1-
b001 /
b00000000001000010010000000 4
b0000000000001000 =
b0000 ?
b00000001 B
b00000000 G
1O
b0000000000001001 S
