hardware/opcode.sv
`define NOP 8'b0000_0000
`define HLT 8'b1111_1111

`define MOV 8'b0000_0001
`define LDA 8'b0000_0010
`define STA 8'b0000_0011

`define ADD 8'b0000_0100
`define SUB 8'b0000_0101
`define MUL 8'b0000_0110
`define DIV 8'b0000_0111

`define AND 8'b0000_1000
`define OR 8'b0000_1001
`define XOR 8'b0000_1010
`define NOT 8'b0000_1011
`define RR 8'b0000_1100

`define PUSH 8'b0000_1101
`define POP 8'b0000_1110

`define JUMP 8'b1000_0000
`define CALL 8'b1010_0000
`define RET 8'b1011_0000

`define NO_REG 3'b000
`define B_REG 3'b001
`define C_REG 3'b010
`define D_REG 3'b001
`define E_REG 3'b100
`define PC_REG 3'b101
`define SP_REG 3'b110
`define A_REG 3'b111

`define NO_OP 4'b0000
`define ADD_OP 4'b0001
`define SUB_OP 4'b0010
`define MUL_OP 4'b0011
`define DIV_OP 4'b0100
`define AND_OP 4'b1000
`define OR_OP 4'b1001
`define XOR_OP 4'b1010
`define NOT_OP 4'b1011
`define RRS_OP 4'b1100
`define RRC_OP 4'b1101
`define LLS_OP 4'b1110
`define LLC_OP 4'b1111

hardware/Control.sv
`include "opcode.sv"

`timescale 1ns / 100ps
`define ROM_ADDR_SIZE 4
`define ROM_DATA_SIZE 26
`define ROM_NUM_INST_SIZE 8
`define ROM_NOTHING `ROM_NUM_INST_SIZE - 1
`define RESET 255
`define STATE_END 255

module ROM (
    input  logic [`ROM_ADDR_SIZE - 1 : 0] rom_addr,
    input  logic [                 2 : 0] read_addr,
    input  logic [                 2 : 0] write_addr,
    output logic [`ROM_DATA_SIZE - 1 : 0] CTRL
);

    logic [`ROM_DATA_SIZE - 1 : 0] read_reg_addr, write_reg_addr;

    always_comb begin
        read_reg_addr  = (read_addr == 3'b111) ? (1'b1 << 25) : ({23'b0, read_addr} << 20);
        write_reg_addr = (write_addr == 3'b111) ? (1'b1 << 24) : ({23'b0, write_addr} << 16);
    end

    // localparam logic [`ROM_DATA_SIZE * (`ROM_NUM_INST_SIZE + 1) - 1:0] memory = {
    localparam logic [`ROM_DATA_SIZE - 1 : 0] memory[`ROM_NUM_INST_SIZE] = {
        /*
         * Acc_Read, Acc_Write,
         * Reg_Read, Reg_Read_Addr[2:0], Reg_Write, Reg_Write_Addr[2:0],
         * Control_Read, Control_Write, Io_Read, IR_Write, IR_Read, MDR_Read, PC_Sel[2:0],
         * ALU_In_1, ALU_In_2, ALU_Op_Sel[3:0], ALU_Out_Write
         */

        // Fetch
        `ROM_DATA_SIZE'b0_0_0_000_0_000_1_0_0_0_0_1_001_0_0_0000_0,  // MDR <- [PC]

        // Decode & Execute
        `ROM_DATA_SIZE'b0_0_1_000_1_000_0_0_0_0_0_0_000_0_0_0000_0,  // Rd <- Rs
        `ROM_DATA_SIZE'b0_0_0_000_0_000_1_0_0_1_0_0_001_0_0_0000_0,  // IR <- data
        `ROM_DATA_SIZE'b0_0_0_000_1_000_0_0_0_0_1_0_000_0_0_0000_0,  // Rd <- IR
        `ROM_DATA_SIZE'b0_0_1_000_0_000_0_0_0_1_0_0_000_0_0_0000_0,  // IR <- Rs
        `ROM_DATA_SIZE'b0_0_0_000_1_000_1_0_1_0_0_0_000_0_0_0000_0,  // Rd <- [IR]
        `ROM_DATA_SIZE'b0_0_1_000_0_000_0_1_0_0_0_0_000_0_0_0000_0,  // [IR] <- Rs

        // END / RESET
        `ROM_DATA_SIZE'b0_0_0_000_0_000_0_0_0_0_0_0_000_0_0_0000_0  // Nothing
    };

    assign CTRL = memory[rom_addr] | read_reg_addr | write_reg_addr;
    // assign CTRL     = memory[ `ROM_DATA_SIZE * rom_addr +: `ROM_DATA_SIZE ] | memory[ `ROM_DATA_SIZE * read_reg_addr +: `ROM_DATA_SIZE ] | memory[ `ROM_DATA_SIZE * write_reg_addr +: `ROM_DATA_SIZE ];
endmodule

module Control #(
    parameter unsigned DATA_WIDTH = 16
) (
    input logic                      reset_n,
    input logic                      clk,
    input logic [DATA_WIDTH - 1 : 0] MDR,
    input logic                      Z_flag,
    input logic                      C_flag,

    output logic         Halt,
    output logic         Acc_Read,
    output logic         Acc_Write,
    output logic         Reg_Read,
    output logic [2 : 0] Reg_Read_Addr,
    output logic         Reg_Write,
    output logic [2 : 0] Reg_Write_Addr,
    output logic         Control_Read,
    output logic         Control_Write,
    output logic         Io_Read,
    output logic         IR_Write,
    output logic         IR_Read,
    output logic         MDR_Read,
    output logic [2 : 0] PC_Sel,
    output logic         ALU_In_1,
    output logic         ALU_In_2,
    output logic [3 : 0] ALU_Op_Sel,
    output logic         ALU_Out_Write
);

    logic [`ROM_ADDR_SIZE - 1 : 0] rom_addr;
    logic [`ROM_DATA_SIZE - 1 : 0] CTRL;

    logic [2 : 0] write_addr, read_addr, param_2, param_1;
    logic param_2_immd, param_1_immd;
    logic [7 : 0] instr;

    logic [7 : 0] state, next_state;

    ROM rom (
        .rom_addr  (rom_addr),
        .read_addr (read_addr),
        .write_addr(write_addr),
        .CTRL      (CTRL)
    );

    assign {instr, param_1_immd, param_1, param_2_immd, param_2} = MDR;

    assign {Acc_Read, Acc_Write,
            Reg_Read, Reg_Read_Addr, Reg_Write, Reg_Write_Addr,
            Control_Read, Control_Write, Io_Read, IR_Write, IR_Read, MDR_Read,
            PC_Sel,
            ALU_In_1, ALU_In_2, ALU_Op_Sel, ALU_Out_Write} = CTRL;

    always_ff @(posedge clk) begin
        if (!reset_n) state <= `RESET;
        else state <= next_state;
    end

    always_ff @(posedge clk) begin
        if (!reset_n) Halt <= 0;
        else if ((state == 1) && (instr == `HLT)) Halt <= 1;
    end

    always_comb begin
        if (!Halt) begin
            case (state)
                // Fetch
                0: begin
                    rom_addr   = 0;
                    write_addr = 0;
                    read_addr  = 0;
                    next_state = 1;
                end

                // Decode & Execute
                1: begin
                    case (instr)
                        `NOP: begin
                            rom_addr   = `ROM_NOTHING;
                            write_addr = 0;
                            read_addr  = 0;
                            next_state = `STATE_END;
                        end
                        `HLT: begin
                            rom_addr   = `ROM_NOTHING;
                            write_addr = 0;
                            read_addr  = 0;
                            next_state = `STATE_END;
                        end
                        `MOV: begin
                            if (param_2_immd == 1'b1) begin
                                rom_addr   = 2;
                                write_addr = 0;
                                read_addr  = 0;
                                next_state = 2;
                            end else begin
                                rom_addr   = 1;
                                write_addr = param_1;
                                read_addr  = param_2;
                                next_state = `STATE_END;
                            end
                        end
                        `LDA: begin
                            rom_addr   = (param_2_immd == 1'b1) ? 2 : 4;
                            write_addr = 0;
                            read_addr  = param_2;
                            next_state = 2;
                        end
                        `STA: begin
                            rom_addr   = (param_1_immd == 1'b1) ? 2 : 4;
                            write_addr = 0;
                            read_addr  = param_1;
                            next_state = 2;
                        end
                        default: begin
                            rom_addr   = `ROM_NOTHING;
                            write_addr = 0;
                            read_addr  = 0;
                            next_state = `STATE_END;
                        end
                    endcase
                end
                2: begin
                    case (instr)
                        `MOV: begin
                            rom_addr   = 3;
                            write_addr = param_1;
                            read_addr  = 0;
                            next_state = `STATE_END;
                        end
                        `LDA: begin
                            rom_addr   = 5;
                            write_addr = param_1;
                            read_addr  = 0;
                            next_state = `STATE_END;
                        end
                        `STA: begin
                            rom_addr   = 6;
                            write_addr = 0;
                            read_addr  = param_2;
                            next_state = `STATE_END;
                        end
                        default: begin
                            rom_addr   = `ROM_NOTHING;
                            write_addr = 0;
                            read_addr  = 0;
                            next_state = `STATE_END;
                        end
                    endcase
                end

                // End / Reset Cycle
                `RESET: begin
                    rom_addr   = `ROM_NOTHING;
                    write_addr = 0;
                    read_addr  = 0;
                    next_state = 0;
                end

                default: begin
                end
            endcase
        end
    end

endmodule

hardware/Register.sv
`timescale 1ns / 100ps

typedef struct packed {
    logic [16 - 1 : 0] SP;
    logic [16 - 1 : 0] PC;
    logic [16 - 1 : 0] E_reg;
    logic [16 - 1 : 0] D_reg;
    logic [16 - 1 : 0] C_reg;
    logic [16 - 1 : 0] B_reg;
} register_def_t;

typedef union packed {
    register_def_t    reg_list;
    logic   [ 6 * 16 - 1 : 0 ] reg_array;
} register_file_t;

module Register #(
    parameter unsigned DATA_WIDTH = 16
) (
    input                             clk,
    input  logic                      write,
    input  logic                      read,
    input  logic                      reset_n,
    input  logic [             2 : 0] addr_read,
    input  logic [             2 : 0] addr_write,
    input  logic [DATA_WIDTH - 1 : 0] data_write,
    output logic [DATA_WIDTH - 1 : 0] data_read
);

    register_file_t register_file;

    // debug
    logic [16 - 1 : 0] B_reg_debug;
    logic [16 - 1 : 0] C_reg_debug;
    logic [16 - 1 : 0] D_reg_debug;
    logic [16 - 1 : 0] E_reg_debug;
    // logic [4 * 16 - 1 : 0] reg_array_debug;

    assign B_reg_debug = register_file.reg_list.B_reg;
    assign C_reg_debug = register_file.reg_list.C_reg;
    assign D_reg_debug = register_file.reg_list.D_reg;
    assign E_reg_debug = register_file.reg_list.E_reg;
    // assign reg_array_debug = register.reg_array;

    always @(posedge clk) begin
        if (!reset_n) register_file <= 'b0;
        else if (write && (addr_write != 'b0))
            register_file[DATA_WIDTH*(addr_write-1)+:DATA_WIDTH] <= data_write;
    end

    assign data_read = (read && (addr_read != 'b0))
                        ? register_file[DATA_WIDTH * ( addr_read - 1 ) +: DATA_WIDTH]
                        : {DATA_WIDTH {1'hz}};

endmodule

hardware/Processor.sv
`timescale 1ns / 100ps

module Processor #(
    parameter unsigned ADDR_WIDTH = 16,
    parameter unsigned DATA_WIDTH = 16
) (
    output logic [ADDR_WIDTH - 1 : 0] address,
    inout  logic [DATA_WIDTH - 1 : 0] data,
    output bit                        read_mem,
    output bit                        write_mem,
    input  bit                        reset_n,
    input  logic                      clk
);

    ////////////////////////  Declaration & Inittialization  ///////////////////////////////
    // Registers & flags
    reg [ADDR_WIDTH - 1 : 0] PC_debug, SP_debug;
    reg [DATA_WIDTH - 1 : 0] MDR, IR, Acc;
    logic Z_flag, C_flag;

    let PC = register.register_file.reg_list.PC;
    let SP = register.register_file.reg_list.SP;
    assign PC_debug = PC;
    assign SP_debug = SP;

    // control signals
    logic Halt;
    logic Acc_Write, Acc_Read, Reg_Write, Reg_Read;
    logic [2 : 0] Reg_Read_Addr, Reg_Write_Addr;
    logic Control_Read, IR_Write, IR_Read, MDR_Read, Io_Read, Control_Write;
    wire [2 : 0] PC_Sel;
    logic ALU_In_1, ALU_In_2, ALU_Out_Write;
    logic [3 : 0] ALU_Op_Sel;

    // interconnect wires & reg
    wire [DATA_WIDTH - 1 : 0] internal_databus;
    logic [ADDR_WIDTH - 1 : 0] next_pc;
    logic [DATA_WIDTH - 1 : 0] ALU_Src_A, ALU_Src_B, ALU_out;

    // ALU
    // Alu alu (
    //     .A_reg     (ALU_Src_A),
    //     .B_reg     (ALU_Src_B),
    //     .op_select (ALU_Op_Sel),
    //     .ALU_output(ALU_out),
    //     .Z_flag    (Z_flag),
    //     .C_flag    (C_flag)
    // );

    // Register File
    Register register (
        .write     (Reg_Write),
        .read      (Reg_Read),
        .reset_n   (reset_n),
        .clk       (clk),
        .data_read (internal_databus),
        .data_write(internal_databus),
        .addr_read (Reg_Read_Addr),
        .addr_write(Reg_Write_Addr)
    );

    // Control Unit
    Control control (
        .reset_n       (reset_n),
        .clk           (clk),
        .MDR           (MDR),
        .Halt          (Halt),
        .Acc_Read      (Acc_Read),
        .Acc_Write     (Acc_Write),
        .Reg_Write     (Reg_Write),
        .Reg_Read      (Reg_Read),
        .Control_Read  (Control_Read),
        .Control_Write (Control_Write),
        .Io_Read       (Io_Read),
        .IR_Write      (IR_Write),
        .IR_Read       (IR_Read),
        .MDR_Read      (MDR_Read),
        .PC_Sel        (PC_Sel),
        .Z_flag        (Z_flag),
        .C_flag        (C_flag),
        .ALU_In_1      (ALU_In_1),
        .ALU_In_2      (ALU_In_2),
        .ALU_Op_Sel    (ALU_Op_Sel),
        .ALU_Out_Write (ALU_Out_Write),
        .Reg_Read_Addr (Reg_Read_Addr),
        .Reg_Write_Addr(Reg_Write_Addr)
    );

    ////////////////////////////////////////////////////////////////////////////////////////

    ////////////////////////  Memory Access  ////////////////////////////

    assign read_mem  = Control_Read;
    assign write_mem = Control_Write;
    always_latch begin
        if (MDR_Read) MDR = internal_databus;
        if (IR_Write) IR = internal_databus;
        if (Acc_Write && Reg_Write) Acc = internal_databus;
    end

    assign internal_databus = Control_Read ? data
                                : (ALU_Out_Write ? ALU_out
                                    : (IR_Read ? IR
                                        : ((Acc_Read && Reg_Read) ? Acc
                                            : {DATA_WIDTH {1'hz}})));

    assign address = Control_Read ? (Io_Read ? IR : PC) : (Control_Write ? IR : {ADDR_WIDTH{1'hz}});
    assign data = Control_Write ? internal_databus : {DATA_WIDTH{1'hz}};

    //////////////////////////////////////////////////////////////////////

    ////////////////////////  ALU  ////////////////////////////

    // always_comb begin
    //     case (ALU_In_1)
    //         1: ALU_Src_A = internal_databus;
    //         default: begin
    //             ALU_Src_A = {DATA_WIDTH{1'b0}};
    //         end
    //     endcase
    //     case (ALU_In_2)
    //         0: ALU_Src_B = internal_databus;
    //         1: ALU_Src_B = IR;
    //         default: begin
    //             ALU_Src_B = {DATA_WIDTH{1'b0}};
    //         end
    //     endcase
    // end

    ///////////////////////////////////////////////////////////

    ////////////////////////  CPU reset Program Counter ////////////////////////////

    always_comb begin
        case (PC_Sel)
            0:       next_pc = PC + {ADDR_WIDTH{1'b0}};
            1:       next_pc = PC + 1'b1;
            2:       next_pc = Z_flag ? IR : PC + 1'b1;
            3:       next_pc = (!Z_flag) ? IR : PC + 1'b1;
            4:       next_pc = (C_flag) ? IR : PC + 1'b1;
            5:       next_pc = (!C_flag) ? IR : PC + 1'b1;
            default: next_pc = PC + {ADDR_WIDTH{1'b0}};
        endcase
    end

    always_ff @(posedge clk) begin
        if (!reset_n) PC <= {ADDR_WIDTH{1'b0}};
        else if (!Halt) PC <= next_pc;
    end

    //////////////////////////////////////////////////////////////////////

endmodule

hardware/Memory.sv
`timescale 1ns / 100ps

module Memory #(
    parameter unsigned ADDR_WIDTH = 16,
    parameter unsigned DATA_WIDTH = 16,
    parameter unsigned DEPTH = 2 ** ADDR_WIDTH
) (
    input logic                      clk,
    input bit                        write,
    input bit                        read,
    input logic [ADDR_WIDTH - 1 : 0] addr,
    inout logic [DATA_WIDTH - 1 : 0] data
);

    logic [DATA_WIDTH - 1 : 0] read_addr;
    logic [DATA_WIDTH - 1 : 0] mem[16];

    always_comb begin
        if (write) mem[addr] = data;
        if (read) read_addr = addr;
    end

    assign data = read ? mem[read_addr] : {DATA_WIDTH{1'hz}};
endmodule

hardware/test_benches/Processor_tb.sv
`timescale 1ns / 100ps

module Processor_tb;
    parameter unsigned ADDR_WIDTH = 16;
    parameter unsigned DATA_WIDTH = 16;


    logic clk, read, write, reset_n;
    logic [ADDR_WIDTH-1:0] addr;
    wire  [DATA_WIDTH-1:0] data;

    Memory memory (
        .write(write),
        .read (read),
        .clk  (clk),
        .addr (addr),
        .data (data)
    );

    Processor u0 (
        .address  (addr),
        .data     (data),
        .read_mem (read),
        .write_mem(write),
        .clk      (clk),
        .reset_n  (reset_n)
    );



    always #1 clk = ~clk;

    initial begin
        clk     = 1;
        reset_n = 1;
        $readmemh("memory.hex", memory.mem, 0);

        #3 reset_n = 0;
        #2 reset_n = 1;
        u0.register.register_file <= 64'h0000000BDEADCAFE;

        #60 $finish;
    end
    initial begin
        $dumpfile("waveform.vcd");
        $dumpvars;
    end

endmodule

hardware/test_benches/waveform.vcd
$version Generated by VerilatedVcd $end
$timescale 100ps $end
 $scope module TOP $end
  $scope module Processor_tb $end
   $var wire 32 e ADDR_WIDTH [31:0] $end
   $var wire 32 e DATA_WIDTH [31:0] $end
   $var wire 1 \ clk $end
   $var wire 1 < read $end
   $var wire 1 = write $end
   $var wire 1 ] reset_n $end
   $var wire 16 ^ addr [15:0] $end
   $var wire 16 _ data [15:0] $end
   $scope module memory $end
    $var wire 32 e ADDR_WIDTH [31:0] $end
    $var wire 32 e DATA_WIDTH [31:0] $end
    $var wire 32 f DEPTH [31:0] $end
    $var wire 1 \ clk $end
    $var wire 1 = write $end
    $var wire 1 < read $end
    $var wire 16 ^ addr [15:0] $end
    $var wire 16 _ data [15:0] $end
    $var wire 16 ` read_addr [15:0] $end
    $var wire 16 # mem[0] [15:0] $end
    $var wire 16 $ mem[1] [15:0] $end
    $var wire 16 % mem[2] [15:0] $end
    $var wire 16 & mem[3] [15:0] $end
    $var wire 16 ' mem[4] [15:0] $end
    $var wire 16 ( mem[5] [15:0] $end
    $var wire 16 ) mem[6] [15:0] $end
    $var wire 16 * mem[7] [15:0] $end
    $var wire 16 + mem[8] [15:0] $end
    $var wire 16 , mem[9] [15:0] $end
    $var wire 16 - mem[10] [15:0] $end
    $var wire 16 . mem[11] [15:0] $end
    $var wire 16 / mem[12] [15:0] $end
    $var wire 16 0 mem[13] [15:0] $end
    $var wire 16 1 mem[14] [15:0] $end
    $var wire 16 2 mem[15] [15:0] $end
   $upscope $end
   $scope module u0 $end
    $var wire 32 e ADDR_WIDTH [31:0] $end
    $var wire 32 e DATA_WIDTH [31:0] $end
    $var wire 16 ^ address [15:0] $end
    $var wire 16 _ data [15:0] $end
    $var wire 1 < read_mem $end
    $var wire 1 = write_mem $end
    $var wire 1 ] reset_n $end
    $var wire 1 \ clk $end
    $var wire 16 3 PC_debug [15:0] $end
    $var wire 16 4 SP_debug [15:0] $end
    $var wire 16 N MDR [15:0] $end
    $var wire 16 O IR [15:0] $end
    $var wire 16 P Acc [15:0] $end
    $var wire 1 g Z_flag $end
    $var wire 1 h C_flag $end
    $var wire 1 a Halt $end
    $var wire 1 > Acc_Write $end
    $var wire 1 ? Acc_Read $end
    $var wire 1 @ Reg_Write $end
    $var wire 1 A Reg_Read $end
    $var wire 3 B Reg_Read_Addr [2:0] $end
    $var wire 3 C Reg_Write_Addr [2:0] $end
    $var wire 1 < Control_Read $end
    $var wire 1 D IR_Write $end
    $var wire 1 E IR_Read $end
    $var wire 1 F MDR_Read $end
    $var wire 1 G Io_Read $end
    $var wire 1 = Control_Write $end
    $var wire 3 H PC_Sel [2:0] $end
    $var wire 1 I ALU_In_1 $end
    $var wire 1 J ALU_In_2 $end
    $var wire 1 K ALU_Out_Write $end
    $var wire 4 L ALU_Op_Sel [3:0] $end
    $var wire 16 b internal_databus [15:0] $end
    $var wire 16 c next_pc [15:0] $end
    $var wire 16 i ALU_Src_A [15:0] $end
    $var wire 16 j ALU_Src_B [15:0] $end
    $var wire 16 k ALU_out [15:0] $end
    $scope module control $end
     $var wire 32 e DATA_WIDTH [31:0] $end
     $var wire 1 ] reset_n $end
     $var wire 1 \ clk $end
     $var wire 16 N MDR [15:0] $end
     $var wire 1 g Z_flag $end
     $var wire 1 h C_flag $end
     $var wire 1 a Halt $end
     $var wire 1 ? Acc_Read $end
     $var wire 1 > Acc_Write $end
     $var wire 1 A Reg_Read $end
     $var wire 3 B Reg_Read_Addr [2:0] $end
     $var wire 1 @ Reg_Write $end
     $var wire 3 C Reg_Write_Addr [2:0] $end
     $var wire 1 < Control_Read $end
     $var wire 1 = Control_Write $end
     $var wire 1 G Io_Read $end
     $var wire 1 D IR_Write $end
     $var wire 1 E IR_Read $end
     $var wire 1 F MDR_Read $end
     $var wire 3 H PC_Sel [2:0] $end
     $var wire 1 I ALU_In_1 $end
     $var wire 1 J ALU_In_2 $end
     $var wire 4 L ALU_Op_Sel [3:0] $end
     $var wire 1 K ALU_Out_Write $end
     $var wire 4 V rom_addr [3:0] $end
     $var wire 26 M CTRL [25:0] $end
     $var wire 3 W write_addr [2:0] $end
     $var wire 3 X read_addr [2:0] $end
     $var wire 3 Q param_2 [2:0] $end
     $var wire 3 R param_1 [2:0] $end
     $var wire 1 S param_2_immd $end
     $var wire 1 T param_1_immd $end
     $var wire 8 U instr [7:0] $end
     $var wire 8 d state [7:0] $end
     $var wire 8 Y next_state [7:0] $end
     $scope module rom $end
      $var wire 4 V rom_addr [3:0] $end
      $var wire 3 X read_addr [2:0] $end
      $var wire 3 W write_addr [2:0] $end
      $var wire 26 M CTRL [25:0] $end
      $var wire 26 Z read_reg_addr [25:0] $end
      $var wire 26 [ write_reg_addr [25:0] $end
      $var wire 26 l memory[0] [25:0] $end
      $var wire 26 m memory[1] [25:0] $end
      $var wire 26 n memory[2] [25:0] $end
      $var wire 26 o memory[3] [25:0] $end
      $var wire 26 p memory[4] [25:0] $end
      $var wire 26 q memory[5] [25:0] $end
      $var wire 26 r memory[6] [25:0] $end
      $var wire 26 s memory[7] [25:0] $end
     $upscope $end
    $upscope $end
    $scope module register $end
     $var wire 32 e DATA_WIDTH [31:0] $end
     $var wire 1 \ clk $end
     $var wire 1 @ write $end
     $var wire 1 A read $end
     $var wire 1 ] reset_n $end
     $var wire 3 B addr_read [2:0] $end
     $var wire 3 C addr_write [2:0] $end
     $var wire 16 b data_write [15:0] $end
     $var wire 16 b data_read [15:0] $end
     $var wire 96 5 register_file [95:0] $end
     $var wire 16 8 B_reg_debug [15:0] $end
     $var wire 16 9 C_reg_debug [15:0] $end
     $var wire 16 : D_reg_debug [15:0] $end
     $var wire 16 ; E_reg_debug [15:0] $end
    $upscope $end
   $upscope $end
  $upscope $end
 $upscope $end
$enddefinitions $end


#0
b0000000000000000 #
b0000001100110001 $
b0000001110000010 %
b0000000000001100 &
b1111111111111111 '
b0000000000000000 (
b0000000000000000 )
b0000000000000000 *
b0000000000000000 +
b0000000000000000 ,
b0000000000000000 -
b0000000000000000 .
b0000000000000000 /
b0000000000000000 0
b0000000000000000 1
b0000000000000000 2
b0000000000000000 3
b0000000000000000 4
b000000000000000000000000000000000000000000000000000000000000000000000000000000000000000000000000 5
b0000000000000000 8
b0000000000000000 9
b0000000000000000 :
b0000000000000000 ;
1<
0=
0>
0?
0@
0A
b000 B
b000 C
0D
0E
1F
0G
b001 H
0I
0J
0K
b0000 L
b00000000001000010010000000 M
b0000000000000000 N
b0000000000000000 O
b0000000000000000 P
b000 Q
b000 R
0S
0T
b00000000 U
b0000 V
b000 W
b000 X
b00000001 Y
b00000000000000000000000000 Z
b00000000000000000000000000 [
1\
1]
b0000000000000000 ^
b0000000000000000 _
b0000000000000000 `
0a
b0000000000000000 b
b0000000000000001 c
b00000000 d
b00000000000000000000000000010000 e
b00000000000000010000000000000000 f
0g
0h
b0000000000000000 i
b0000000000000000 j
b0000000000000000 k
b00000000001000010010000000 l
b00100010000000000000000000 m
b00000000001001000010000000 n
b00000010000000100000000000 o
b00100000000001000000000000 p
b00000010001010000000000000 q
b00100000000100000000000000 r
b00000000000000000000000000 s
#10
0\
#20
b0000000000000001 3
b000000000000000000000000000000010000000000000000000000000000000000000000000000000000000000000000 5
0<
0F
b000 H
b00000000000000000000000000 M
b0111 V
b11111111 Y
1\
b0000000000000001 `
b00000001 d
#30
0\
0]
#40
b0000000000000000 3
b000000000000000000000000000000000000000000000000000000000000000000000000000000000000000000000000 5
b00000000 Y
1\
b0000000000000000 c
b11111111 d
#50
b000000000000000000000000000000000000000000000000000000000000101111011110101011011100101011111110 5
b1100101011111110 8
b1101111010101101 9
b0000000000001011 :
0\
1]
#60
1<
1F
b001 H
b00000000001000010010000000 M
b0000 V
b00000001 Y
1\
b0000000000000000 `
b0000000000000001 c
b00000000 d
#70
0\
#80
b0000000000000001 3
b000000000000000000000000000000010000000000000000000000000000101111011110101011011100101011111110 5
0<
0F
b000 H
b00000000000000000000000000 M
b0111 V
b11111111 Y
1\
b0000000000000001 `
b00000001 d
#90
0\
#100
b00000000 Y
1\
b11111111 d
#110
0\
#120
1<
1F
b001 H
b00000000001000010010000000 M
b0000001100110001 N
b001 Q
b011 R
b00000011 U
b0000 V
b00000001 Y
1\
b0000000000000001 ^
b0000001100110001 _
b0000001100110001 b
b0000000000000010 c
b00000000 d
#130
0\
#140
b0000000000000010 3
b000000000000000000000000000000100000000000000000000000000000101111011110101011011100101011111110 5
0<
1A
b011 B
1D
0F
b000 H
b00101100000001000000000000 M
b0000000000001011 O
b0100 V
b011 X
b00000010 Y
b00001100000000000000000000 Z
1\
b0000000000000000 ^
b0000000000000000 _
b0000000000000010 `
b0000000000001011 b
b00000001 d
#150
0\
#160
b1100101011111110 .
1=
b001 B
0D
b00100100000100000000000000 M
b0110 V
b001 X
b11111111 Y
b00000100000000000000000000 Z
1\
b0000000000001011 ^
b1100101011111110 _
b1100101011111110 b
b00000010 d
#170
0\
#180
0=
0A
b000 B
b00000000000000000000000000 M
b0111 V
b000 X
b00000000 Y
b00000000000000000000000000 Z
1\
b0000000000000000 ^
b0000000000000000 _
b0000000000000000 b
b11111111 d
#190
0\
#200
1<
1F
b001 H
b00000000001000010010000000 M
b0000001110000010 N
b010 Q
b000 R
1T
b0000 V
b00000001 Y
1\
b0000000000000010 ^
b0000001110000010 _
b0000001110000010 b
b0000000000000011 c
b00000000 d
#210
0\
#220
b0000000000000011 3
b000000000000000000000000000000110000000000000000000000000000101111011110101011011100101011111110 5
1D
0F
b00000000001001000010000000 M
b0000000000001100 O
b0010 V
b00000010 Y
1\
b0000000000000011 ^
b0000000000001100 _
b0000000000000011 `
b0000000000001100 b
b0000000000000100 c
b00000001 d
#230
0\
#240
b1101111010101101 /
b0000000000000100 3
b000000000000000000000000000001000000000000000000000000000000101111011110101011011100101011111110 5
0<
1=
1A
b010 B
0D
b000 H
b00101000000100000000000000 M
b0110 V
b010 X
b11111111 Y
b00001000000000000000000000 Z
1\
b0000000000001100 ^
b1101111010101101 _
b0000000000000100 `
b1101111010101101 b
b00000010 d
#250
0\
#260
0=
0A
b000 B
b00000000000000000000000000 M
b0111 V
b000 X
b00000000 Y
b00000000000000000000000000 Z
1\
b0000000000000000 ^
b0000000000000000 _
b0000000000000000 b
b11111111 d
#270
0\
#280
1<
1F
b001 H
b00000000001000010010000000 M
b1111111111111111 N
b111 Q
b111 R
1S
b11111111 U
b0000 V
b00000001 Y
1\
b0000000000000100 ^
b1111111111111111 _
b1111111111111111 b
b0000000000000101 c
b00000000 d
#290
0\
#300
b0000000000000101 3
b000000000000000000000000000001010000000000000000000000000000101111011110101011011100101011111110 5
0<
0F
b000 H
b00000000000000000000000000 M
b0111 V
b11111111 Y
1\
b0000000000000000 ^
b0000000000000000 _
b0000000000000101 `
b0000000000000000 b
b00000001 d
#310
0\
#320
1\
1a
b11111111 d
