hardware/opcode.sv
`define NOP 8'b0000_0000
`define HLT 8'b1111_1111

`define MOV 8'b0000_0001
`define LDA 8'b0000_0010
`define STA 8'b0000_0011

`define ADD 8'b0000_0100
`define SUB 8'b0000_0101
`define MUL 8'b0000_0110
`define DIV 8'b0000_0111

`define AND 8'b0000_1000
`define OR 8'b0000_1001
`define XOR 8'b0000_1010
`define NOT 8'b0000_1011
`define RR 8'b0000_1100

`define PUSH 8'b0000_1101
`define POP 8'b0000_1110

`define JUMP 8'b1000_0000
`define CALL 8'b1010_0000
`define RET 8'b1011_0000

`define NO_REG 3'b000
`define B_REG 3'b001
`define C_REG 3'b010
`define D_REG 3'b001
`define E_REG 3'b100
`define PC_REG 3'b101
`define SP_REG 3'b110
`define A_REG 3'b111

`define NO_OP 4'b0000
`define ADD_OP 4'b0001
`define SUB_OP 4'b0010
`define MUL_OP 4'b0011
`define DIV_OP 4'b0100
`define AND_OP 4'b1000
`define OR_OP 4'b1001
`define XOR_OP 4'b1010
`define NOT_OP 4'b1011
`define RRS_OP 4'b1100
`define RRC_OP 4'b1101
`define LLS_OP 4'b1110
`define LLC_OP 4'b1111

hardware/Control.sv
`include "opcode.sv"

`timescale 1ns / 100ps
`define ROM_ADDR_SIZE 32
`define ROM_DATA_SIZE 24
`define ROM_NUM_INST_SIZE 11

module ROM (
    input  logic [`ROM_ADDR_SIZE - 1 : 0] rom_addr,
    input  logic [                 3 : 0] param_1_addr,
    input  logic [                 3 : 0] param_2_addr,
    output logic [`ROM_DATA_SIZE - 1 : 0] CTRL
);

    logic [3 : 0] read_reg_addr, write_reg_addr;
    always_comb begin
        read_reg_addr = (param_1_addr != 4'h0) ? ((`ROM_NUM_INST_SIZE - 1) - 3 - param_1_addr) : (`ROM_NUM_INST_SIZE - 1);
        write_reg_addr = (param_2_addr != 4'h0) ? ((`ROM_NUM_INST_SIZE - 1) - param_2_addr) : (`ROM_NUM_INST_SIZE - 1);
        $display(
            "[rom] time = %03t, rom_addr : %02h, param_1_addr : %0h, read_reg_addr : %0h, param_2_addr : %0h, write_reg_addr : %0h",
            $time, rom_addr, param_1_addr, read_reg_addr, param_2_addr, write_reg_addr);
    end
    // localparam logic [`ROM_DATA_SIZE * (`ROM_NUM_INST_SIZE + 1) - 1:0] memory = {
    localparam logic [`ROM_DATA_SIZE - 1:0] memory[`ROM_NUM_INST_SIZE] = {
        /*
         * Reg_Read, Reg_Read_Addr[2:0], Reg_Write, Reg_Write_Addr[2:0],
         * Control_Read, Control_Write, Io_Read, IR_Read, IR_Write, MDR_Read, PC_Sel[2:0],
         * ALU_In_1, ALU_In_2, ALU_Op_Sel[3:0], ALU_Out_Write
         */

        `ROM_DATA_SIZE'b0_000_0_000_1_0_0_0_0_1_001_0_0_0000_0,  // MDR <- [PC]
        `ROM_DATA_SIZE'b1_000_1_000_0_0_0_0_0_0_001_0_0_0000_0,  // Rd <- Rs
        `ROM_DATA_SIZE'b0_000_0_000_1_0_0_1_0_0_001_0_0_0000_0,  // IR <- data
        `ROM_DATA_SIZE'b0_000_1_000_0_0_0_0_1_0_001_0_0_0000_0,  // Rd <- IR

        /* Read Register select */
        `ROM_DATA_SIZE'b0_011_0_000_0_0_0_0_0_0_000_0_0_0000_0,  // C
        `ROM_DATA_SIZE'b0_010_0_000_0_0_0_0_0_0_000_0_0_0000_0,  // B
        `ROM_DATA_SIZE'b0_001_0_000_0_0_0_0_0_0_000_0_0_0000_0,  // A

        /* Write Register select */
        `ROM_DATA_SIZE'b0_000_0_011_0_0_0_0_0_0_000_0_0_0000_0,  // C
        `ROM_DATA_SIZE'b0_000_0_010_0_0_0_0_0_0_000_0_0_0000_0,  // B
        `ROM_DATA_SIZE'b0_000_0_001_0_0_0_0_0_0_000_0_0_0000_0,  // A

        `ROM_DATA_SIZE'b0_000_0_000_0_0_0_0_0_0_000_0_0_0000_0  // NOTHING
    };

    assign CTRL = memory[rom_addr] | memory[read_reg_addr] | memory[write_reg_addr];
endmodule

module Control #(
    parameter unsigned DATA_WIDTH = 16
) (
    input logic                      reset_n,
    input logic                      clk,
    input logic [DATA_WIDTH - 1 : 0] MDR,
    input logic                      Z_flag,
    input logic                      C_flag,

    output logic         Reg_Read,
    output logic [2 : 0] Reg_Read_Addr,
    output logic         Reg_Write,
    output logic [2 : 0] Reg_Write_Addr,

    output logic         Control_Read,
    output logic         Control_Write,
    output logic         Io_Read,
    output logic         IR_Read,
    output logic         IR_Write,
    output logic         MDR_Read,
    output logic [2 : 0] PC_Sel,

    output logic         ALU_In_1,
    output logic         ALU_In_2,
    output logic [3 : 0] ALU_Op_Sel,
    output logic         ALU_Out_Write
);

    logic [`ROM_ADDR_SIZE - 1 : 0] rom_addr;
    logic [`ROM_DATA_SIZE - 1 : 0] CTRL;

    logic [3 : 0] param_2, param_1, param_2_addr, param_1_addr;
    logic [7 : 0] instr;

    logic [7 : 0] state;

    ROM rom (
        .rom_addr    (rom_addr),
        .param_1_addr(param_1_addr),
        .param_2_addr(param_2_addr),
        .CTRL        (CTRL)
    );

    initial begin
        state = 'h00;
        CTRL  = 0;
    end


    assign {instr, param_1, param_2} = MDR;

    assign {
        Reg_Read, Reg_Read_Addr, Reg_Write, Reg_Write_Addr,
        Control_Read, Control_Write, Io_Read, IR_Read, IR_Write, MDR_Read, PC_Sel,
        ALU_In_1, ALU_In_2, ALU_Op_Sel, ALU_Out_Write
    } = CTRL;

    always_ff @(posedge clk) begin
        $display("break");
        $display(
            "[state] time = %03t, reset_n : %b, state : %d, instr : %02h rom_addr : %02h, param_1_addr : %0h, param_2_addr : %0h",
            $time, reset_n, state, instr, rom_addr, param_1_addr, param_2_addr);
        // $strobe(
        //     "[strobe]  time = %0t, reset_n : %b, state : %d, instr : %0h rom_addr : %0h, param_1_addr : %0h, param_2_addr : %0h",
        //     $time, reset_n, state, instr, rom_addr, param_1_addr, param_2_addr);
        if (!reset_n) state <= 0;
        case (state)
            0: begin
                rom_addr     <= `ROM_NUM_INST_SIZE - 1;
                param_1_addr <= 0;
                param_2_addr <= 0;
                state        <= 1;
            end
            1: begin
                case (instr)
                    `NOP: begin
                        rom_addr     <= 0;
                        param_1_addr <= 0;
                        param_2_addr <= 0;
                        state        <= 0;
                    end
                    `MOV: begin
                        if (param_2 == {1'b0, `IR_REG}) begin
                            rom_addr     <= 2;
                            param_1_addr <= 0;
                            param_2_addr <= 0;
                            state        <= 2;
                        end else begin
                            rom_addr     <= 1;
                            param_1_addr <= param_1;
                            param_2_addr <= param_2;
                            state        <= 0;
                        end

                    end
                    default: begin
                        rom_addr     <= 0;
                        param_1_addr <= 0;
                        param_2_addr <= 0;
                        state        <= 0;
                    end
                endcase
            end
            2: begin
                case (instr)
                    `MOV: begin
                        rom_addr     <= 3;
                        param_1_addr <= 0;
                        param_2_addr <= param_1;
                        state        <= 0;
                    end
                    default: begin
                        rom_addr     <= 0;
                        param_1_addr <= 0;
                        param_2_addr <= 0;
                        state        <= 0;
                    end
                endcase
            end
            // Execute Cycles

            default: begin
                rom_addr     <= 0;
                param_1_addr <= 0;
                param_2_addr <= 0;
            end
        endcase
    end

endmodule

hardware/Register.sv
`timescale 1ns / 100ps

module Register #(
    parameter unsigned DATA_WIDTH = 16
) (
    input                       write,
    input                       read,
    input                       reset_n,
    input  [             2 : 0] addr_read,
    input  [             2 : 0] addr_write,
    input  [DATA_WIDTH - 1 : 0] data_write,
    output [DATA_WIDTH - 1 : 0] data_read,
    input                       clk
);

    logic [3 * DATA_WIDTH - 1 : 0] register;

    always @(posedge clk) begin
        if (!reset_n) register <= 'b0;
        else if (write) register[DATA_WIDTH*(addr_write-1)+:DATA_WIDTH] <= data_write;
    end

    assign data_read = read ? register[DATA_WIDTH*(addr_read-1)+:DATA_WIDTH] : {DATA_WIDTH{1'hz}};

endmodule

hardware/Processor.sv
`timescale 1ns / 100ps

module Processor #(
    parameter unsigned ADDR_WIDTH = 16,
    parameter unsigned DATA_WIDTH = 16
) (
    output logic [ADDR_WIDTH - 1:0] address,
    inout  logic [DATA_WIDTH - 1:0] data,
    output bit                      read_mem,
    output bit                      write_mem,
    input  bit                      reset_n,
    input  logic                    clk
);

    ////////////////////////  Declaration & Inittialization  ///////////////////////////////
    // Registers & flags
    reg [ADDR_WIDTH - 1 : 0] PC, SP;
    reg [DATA_WIDTH - 1 : 0] MDR, IR;
    logic Z_flag, C_flag;

    // control signals
    logic
        Reg_Write,
        Reg_Read,
        Control_Read,
        IR_Read,
        IR_Write,
        MDR_Read,
        Io_Read,
        Control_Write,
        ALU_In_1,
        ALU_In_2,
        ALU_Out_Write;
    logic [2:0] PC_Sel;
    logic [3:0] ALU_Op_Sel;
    logic [2 : 0] Reg_Read_Addr, Reg_Write_Addr;

    // interconnect wires & reg
    logic [DATA_WIDTH - 1 : 0] internal_databus;
    logic [ADDR_WIDTH - 1 : 0] next_pc;
    logic [DATA_WIDTH - 1 : 0] ALU_Src_A, ALU_Src_B, ALU_out;

    // ALU
    // Alu alu (
    //     .A_reg     (ALU_Src_A),
    //     .B_reg     (ALU_Src_B),
    //     .op_select (ALU_Op_Sel),
    //     .ALU_output(ALU_out),
    //     .Z_flag    (Z_flag),
    //     .C_flag    (C_flag)
    // );

    // Register File
    Register register (
        .write     (Reg_Write),
        .read      (Reg_Read),
        .reset_n   (reset_n),
        .clk       (clk),
        .data_read (internal_databus),
        .data_write(internal_databus),
        .addr_read (Reg_Read_Addr),
        .addr_write(Reg_Write_Addr)
    );

    // Control Unit
    Control control (
        .reset_n       (reset_n),
        .clk           (clk),
        .MDR           (MDR),
        .Reg_Write     (Reg_Write),
        .Reg_Read      (Reg_Read),
        .Control_Read  (Control_Read),
        .Control_Write (Control_Write),
        .Io_Read       (Io_Read),
        .IR_Read       (IR_Read),
        .IR_Write      (IR_Write),
        .MDR_Read      (MDR_Read),
        .PC_Sel        (PC_Sel),
        .Z_flag        (Z_flag),
        .C_flag        (C_flag),
        .ALU_In_1      (ALU_In_1),
        .ALU_In_2      (ALU_In_2),
        .ALU_Op_Sel    (ALU_Op_Sel),
        .ALU_Out_Write (ALU_Out_Write),
        .Reg_Read_Addr (Reg_Read_Addr),
        .Reg_Write_Addr(Reg_Write_Addr)
    );

    ////////////////////////////////////////////////////////////////////////////////////////

    ////////////////////////  Memory Access  ////////////////////////////

    // Read from memory (via pointer in register) to a register
    always_comb begin
        if (read_mem) assign internal_databus = data;
        else if (ALU_Out_Write) assign internal_databus = ALU_out;
        else if (IR_Write) assign internal_databus = IR;
        else assign internal_databus = {DATA_WIDTH{1'hz}};
    end

    // Write to memory (via pointer in register) from a register
    assign data = write_mem ? internal_databus : {DATA_WIDTH{1'hz}};

    always_ff @(posedge clk) begin
        if (Control_Read) begin
            address  <= Io_Read ? IR : PC;
            read_mem <= 1;
            if (MDR_Read) MDR <= internal_databus;
            if (IR_Read) IR <= internal_databus;
        end else begin
            read_mem <= 0;
        end

        if (Control_Write) begin
            address   <= IR;
            write_mem <= 1;
        end else begin
            write_mem <= 0;
        end
    end

    //////////////////////////////////////////////////////////////////////

    ////////////////////////  ALU  ////////////////////////////

    // always_comb begin
    //     case (ALU_In_1)
    //         1: ALU_Src_A = internal_databus;
    //         default: begin
    //             ALU_Src_A = {DATA_WIDTH{1'b0}};
    //         end
    //     endcase
    //     case (ALU_In_2)
    //         0: ALU_Src_B = internal_databus;
    //         1: ALU_Src_B = IR;
    //         default: begin
    //             ALU_Src_B = {DATA_WIDTH{1'b0}};
    //         end
    //     endcase
    // end

    ///////////////////////////////////////////////////////////

    ////////////////////////  CPU reset Program Counter ////////////////////////////

    always_comb begin
        case (PC_Sel)
            0: next_pc = PC + {ADDR_WIDTH{1'b0}};
            1: next_pc = PC + 1'b1;
            2: next_pc = Z_flag ? IR : PC + 1'b1;
            3: next_pc = (!Z_flag) ? IR : PC + 1'b1;
            4: next_pc = (C_flag) ? IR : PC + 1'b1;
            5: next_pc = (!C_flag) ? IR : PC + 1'b1;
            default: begin
            end
        endcase
    end

    always @(posedge clk) begin
        if (!reset_n) PC <= {ADDR_WIDTH{1'b0}};
        else PC <= next_pc;

    end

    //////////////////////////////////////////////////////////////////////


endmodule

hardware/Memory.sv
`timescale 1ns / 100ps

module Memory #(
    parameter unsigned ADDR_WIDTH = 16,
    parameter unsigned DATA_WIDTH = 16,
    parameter unsigned DEPTH = 2 ** ADDR_WIDTH
) (
    input bit                    write,
    input bit                    read,
    input logic                  clk,
    input logic [ADDR_WIDTH-1:0] addr,
    inout logic [DATA_WIDTH-1:0] data
);

    logic [DATA_WIDTH-1:0] tmp_data;
    logic [DATA_WIDTH-1:0] mem[5];

    always @(posedge clk) begin
        if (write) mem[addr] <= data;
    end

    always @(posedge clk) begin
        if (read) tmp_data <= mem[addr];
    end

    assign data = (!write && read) ? tmp_data : {DATA_WIDTH{1'hz}};

endmodule

hardware/test_benches/Processor_tb.sv
`timescale 1ns / 100ps

module Processor_tb;
    parameter unsigned ADDR_WIDTH = 16;
    parameter unsigned DATA_WIDTH = 16;


    logic clk, read, write, reset_n;
    logic [ADDR_WIDTH-1:0] addr;
    wire  [DATA_WIDTH-1:0] data;

    Memory memory (
        .write(write),
        .read (read),
        .clk  (clk),
        .addr (addr),
        .data (data)
    );

    Processor u0 (
        .address  (addr),
        .data     (data),
        .read_mem (read),
        .write_mem(write),
        .clk      (clk),
        .reset_n  (reset_n)
    );



    always #1 clk = ~clk;

    initial begin
        clk     = 1;
        reset_n = 1;
        $readmemh("memory.hex", memory.mem, 0);

        #3 reset_n = 0;
        #2 reset_n = 1;
        u0.register.register_file <= 64'h0000000BDEADCAFE;

        #60 $finish;
    end
    initial begin
        $dumpfile("waveform.vcd");
        $dumpvars;
    end

endmodule

hardware/test_benches/waveform.vcd
$version Generated by VerilatedVcd $end
$timescale 100ps $end
 $scope module TOP $end
  $scope module Processor_tb $end
   $var wire 32 O ADDR_WIDTH [31:0] $end
   $var wire 32 O DATA_WIDTH [31:0] $end
   $var wire 1 E clk $end
   $var wire 1 4 read $end
   $var wire 1 5 write $end
   $var wire 1 F reset_n $end
   $var wire 16 6 addr [15:0] $end
   $var wire 16 G data [15:0] $end
   $scope module memory $end
    $var wire 32 O ADDR_WIDTH [31:0] $end
    $var wire 32 O DATA_WIDTH [31:0] $end
    $var wire 32 P DEPTH [31:0] $end
    $var wire 1 5 write $end
    $var wire 1 4 read $end
    $var wire 1 E clk $end
    $var wire 16 6 addr [15:0] $end
    $var wire 16 G data [15:0] $end
    $var wire 16 H tmp_data [15:0] $end
    $var wire 16 I mem[0] [15:0] $end
    $var wire 16 J mem[1] [15:0] $end
    $var wire 16 K mem[2] [15:0] $end
    $var wire 16 L mem[3] [15:0] $end
    $var wire 16 M mem[4] [15:0] $end
   $upscope $end
   $scope module u0 $end
    $var wire 32 O ADDR_WIDTH [31:0] $end
    $var wire 32 O DATA_WIDTH [31:0] $end
    $var wire 16 6 address [15:0] $end
    $var wire 16 G data [15:0] $end
    $var wire 1 4 read_mem $end
    $var wire 1 5 write_mem $end
    $var wire 1 F reset_n $end
    $var wire 1 E clk $end
    $var wire 16 7 PC [15:0] $end
    $var wire 16 Q SP [15:0] $end
    $var wire 16 8 MDR [15:0] $end
    $var wire 16 9 IR [15:0] $end
    $var wire 1 R Z_flag $end
    $var wire 1 S C_flag $end
    $var wire 1 # Reg_Write $end
    $var wire 1 $ Reg_Read $end
    $var wire 1 % Control_Read $end
    $var wire 1 & IR_Read $end
    $var wire 1 ' IR_Write $end
    $var wire 1 ( MDR_Read $end
    $var wire 1 ) Io_Read $end
    $var wire 1 * Control_Write $end
    $var wire 1 + ALU_In_1 $end
    $var wire 1 , ALU_In_2 $end
    $var wire 1 - ALU_Out_Write $end
    $var wire 3 . PC_Sel [2:0] $end
    $var wire 4 / ALU_Op_Sel [3:0] $end
    $var wire 3 0 Reg_Read_Addr [2:0] $end
    $var wire 3 1 Reg_Write_Addr [2:0] $end
    $var wire 16 N internal_databus [15:0] $end
    $var wire 16 : next_pc [15:0] $end
    $var wire 16 T ALU_Src_A [15:0] $end
    $var wire 16 U ALU_Src_B [15:0] $end
    $var wire 16 V ALU_out [15:0] $end
    $scope module control $end
     $var wire 32 O DATA_WIDTH [31:0] $end
     $var wire 1 F reset_n $end
     $var wire 1 E clk $end
     $var wire 16 8 MDR [15:0] $end
     $var wire 1 R Z_flag $end
     $var wire 1 S C_flag $end
     $var wire 1 $ Reg_Read $end
     $var wire 3 0 Reg_Read_Addr [2:0] $end
     $var wire 1 # Reg_Write $end
     $var wire 3 1 Reg_Write_Addr [2:0] $end
     $var wire 1 % Control_Read $end
     $var wire 1 * Control_Write $end
     $var wire 1 ) Io_Read $end
     $var wire 1 & IR_Read $end
     $var wire 1 ' IR_Write $end
     $var wire 1 ( MDR_Read $end
     $var wire 3 . PC_Sel [2:0] $end
     $var wire 1 + ALU_In_1 $end
     $var wire 1 , ALU_In_2 $end
     $var wire 4 / ALU_Op_Sel [3:0] $end
     $var wire 1 - ALU_Out_Write $end
     $var wire 32 ; rom_addr [31:0] $end
     $var wire 24 2 CTRL [23:0] $end
     $var wire 4 < param_2 [3:0] $end
     $var wire 4 = param_1 [3:0] $end
     $var wire 4 > param_2_addr [3:0] $end
     $var wire 4 ? param_1_addr [3:0] $end
     $var wire 8 @ instr [7:0] $end
     $var wire 8 3 state [7:0] $end
     $scope module rom $end
      $var wire 32 ; rom_addr [31:0] $end
      $var wire 4 ? param_1_addr [3:0] $end
      $var wire 4 > param_2_addr [3:0] $end
      $var wire 24 2 CTRL [23:0] $end
      $var wire 4 A read_reg_addr [3:0] $end
      $var wire 4 B write_reg_addr [3:0] $end
      $var wire 24 W memory[0] [23:0] $end
      $var wire 24 X memory[1] [23:0] $end
      $var wire 24 Y memory[2] [23:0] $end
      $var wire 24 Z memory[3] [23:0] $end
      $var wire 24 [ memory[4] [23:0] $end
      $var wire 24 \ memory[5] [23:0] $end
      $var wire 24 ] memory[6] [23:0] $end
      $var wire 24 ^ memory[7] [23:0] $end
      $var wire 24 _ memory[8] [23:0] $end
      $var wire 24 ` memory[9] [23:0] $end
      $var wire 24 a memory[10] [23:0] $end
     $upscope $end
    $upscope $end
    $scope module register $end
     $var wire 32 O DATA_WIDTH [31:0] $end
     $var wire 1 # write $end
     $var wire 1 $ read $end
     $var wire 1 F reset_n $end
     $var wire 3 0 addr_read [2:0] $end
     $var wire 3 1 addr_write [2:0] $end
     $var wire 16 N data_write [15:0] $end
     $var wire 16 N data_read [15:0] $end
     $var wire 1 E clk $end
     $var wire 48 C register [47:0] $end
    $upscope $end
   $upscope $end
  $upscope $end
 $upscope $end
$enddefinitions $end


#0
0#
0$
1%
0&
0'
1(
0)
0*
0+
0,
0-
b001 .
b0000 /
b000 0
b000 1
b000000001000010010000000 2
b00000000 3
04
05
b0000000000000000 6
b0000000000000000 7
b0000000000000000 8
b0000000000000000 9
b0000000000000001 :
b00000000000000000000000000000000 ;
b0000 <
b0000 =
b0000 >
b0000 ?
b00000000 @
b1010 A
b1010 B
b000000000000000000000000000000000000000000000000 C
0E
0F
b0000000000000000 G
b0000000000000000 H
b0000000000000000 I
b0000000100100100 J
b1100101011111110 K
b0000000100010010 L
b1111111111111111 M
b0000000000000000 N
b00000000000000000000000000010000 O
b00000000000000010000000000000000 P
b0000000000000000 Q
0R
0S
b0000000000000000 T
b0000000000000000 U
b0000000000000000 V
b000000001000010010000000 W
b100010000000000010000000 X
b000000001001000010000000 Y
b000010000000100010000000 Z
b001100000000000000000000 [
b001000000000000000000000 \
b000100000000000000000000 ]
b000000110000000000000000 ^
b000000100000000000000000 _
b000000010000000000000000 `
b000000000000000000000000 a
#5
1F
#10
0%
0(
b000 .
b000000000000000000000000 2
b00000001 3
14
b0000000000000001 7
b00000000000000000000000000001010 ;
1E
#20
0E
#30
1%
1(
b001 .
b000000001000010010000000 2
b00000000 3
04
b0000000000000010 :
b00000000000000000000000000000000 ;
1E
#40
0E
#50
0%
0(
b000 .
b000000000000000000000000 2
b00000001 3
14
b0000000000000001 6
b0000000000000010 7
b00000000000000000000000000001010 ;
1E
b0000000100100100 G
b0000000100100100 H
b0000000100100100 N
#60
0E
#70
1%
1(
b001 .
b000000001000010010000000 2
b00000000 3
04
b0000000000000011 :
b00000000000000000000000000000000 ;
1E
b0000000000000000 G
b0000000000000000 N
#80
0E
#90
0%
0(
b000 .
b000000000000000000000000 2
b00000001 3
14
b0000000000000010 6
b0000000000000011 7
b00000000000000000000000000001010 ;
1E
b1100101011111110 G
b1100101011111110 H
b1100101011111110 N
#100
0E
#110
1%
1(
b001 .
b000000001000010010000000 2
b00000000 3
04
b0000000000000100 :
b00000000000000000000000000000000 ;
1E
b0000000000000000 G
b0000000000000000 N
#120
0E
#130
0%
0(
b000 .
b000000000000000000000000 2
b00000001 3
14
b0000000000000011 6
b0000000000000100 7
b00000000000000000000000000001010 ;
1E
b0000000100010010 G
b0000000100010010 H
b0000000100010010 N
#140
0E
#150
1%
1(
b001 .
b000000001000010010000000 2
b00000000 3
04
b0000000000000101 :
b00000000000000000000000000000000 ;
1E
b0000000000000000 G
b0000000000000000 N
#160
0E
#170
0%
0(
b000 .
b000000000000000000000000 2
b00000001 3
14
b0000000000000100 6
b0000000000000101 7
b00000000000000000000000000001010 ;
1E
b1111111111111111 G
b1111111111111111 H
b1111111111111111 N
#180
0E
#190
1%
1(
b001 .
b000000001000010010000000 2
b00000000 3
04
b0000000000000110 :
b00000000000000000000000000000000 ;
1E
b0000000000000000 G
b0000000000000000 N
#200
0E
#210
0%
0(
b000 .
b000000000000000000000000 2
b00000001 3
14
b0000000000000101 6
b0000000000000110 7
b00000000000000000000000000001010 ;
1E
b0000000000000000 H
#220
0E
#230
1%
1(
b001 .
b000000001000010010000000 2
b00000000 3
04
b0000000000000111 :
b00000000000000000000000000000000 ;
1E
#240
0E
#250
0%
0(
b000 .
b000000000000000000000000 2
b00000001 3
14
b0000000000000110 6
b0000000000000111 7
b00000000000000000000000000001010 ;
1E
#260
0E
#270
1%
1(
b001 .
b000000001000010010000000 2
b00000000 3
04
b0000000000001000 :
b00000000000000000000000000000000 ;
1E
#280
0E
#290
0%
0(
b000 .
b000000000000000000000000 2
b00000001 3
14
b0000000000000111 6
b0000000000001000 7
b00000000000000000000000000001010 ;
1E
