hardware/opcode.sv
`define NOP 8'b0000_0000
`define HLT 8'b1111_1111

`define MOV 8'b0000_0001
`define LDA 8'b0000_0010
`define STA 8'b0000_0011

`define ADD 8'b0000_0100
`define SUB 8'b0000_0101
`define MUL 8'b0000_0110
`define DIV 8'b0000_0111

`define AND 8'b0000_1000
`define OR 8'b0000_1001
`define XOR 8'b0000_1010
`define NOT 8'b0000_1011
`define RR 8'b0000_1100

`define PUSH 8'b0000_1101
`define POP 8'b0000_1110

`define JUMP 8'b1000_0000
`define CALL 8'b1010_0000
`define RET 8'b1011_0000

`define NO_REG 3'b000
`define A_REG 3'b001
`define B_REG 3'b010
`define C_REG 3'b001
`define IR_REG 3'b100
`define PC_REG 3'b101
`define SP_REG 3'b110
`define MDR_REG 3'b111

`define NO_OP 4'b0000
`define ADD_OP 4'b0001
`define SUB_OP 4'b0010
`define MUL_OP 4'b0011
`define DIV_OP 4'b0100
`define AND_OP 4'b1000
`define OR_OP 4'b1001
`define XOR_OP 4'b1010
`define NOT_OP 4'b1011
`define RRS_OP 4'b1100
`define RRC_OP 4'b1101
`define LLS_OP 4'b1110
`define LLC_OP 4'b1111

hardware/Control.sv
`include "opcode.sv"

`timescale 1ns / 100ps
`define ROM_ADDR_SIZE 32
`define ROM_DATA_SIZE 24
`define ROM_NUM_INST_SIZE 11

module ROM (
    input  logic [`ROM_ADDR_SIZE - 1 : 0] rom_addr,
    input  logic [                 2 : 0] read_reg_sel_addr,
    input  logic [                 2 : 0] write_reg_sel_addr,
    output logic [`ROM_DATA_SIZE - 1 : 0] CTRL
);

    logic [`ROM_DATA_SIZE - 1 : 0] read_reg_addr = (`ROM_NUM_INST_SIZE - 1) - 7 + read_reg_sel_addr;
    logic [`ROM_DATA_SIZE - 1 : 0] write_reg_addr = (`ROM_NUM_INST_SIZE - 1) - 4 + write_reg_sel_addr;
    // parameter [`ROM_DATA_SIZE * (`ROM_NUM_INST_SIZE + 1) - 1:0] memory = {
    logic [`ROM_DATA_SIZE - 1:0] memory[`ROM_NUM_INST_SIZE] = {
        /*
         * Reg_Read, Reg_Read_Addr[2:0], Reg_Write, Reg_Write_Addr[2:0],
         * Control_Read, Control_Write, Io_Read, IR_Read, IR_Write, MDR_Read, PC_Sel[2:0],
         * ALU_In_1, ALU_In_2, ALU_Op_Sel[3:0], ALU_Out_Write
         */

        `ROM_DATA_SIZE'b0_000_0_000_1_0_0_0_0_1_000_0_0_0000_0,  // MDR <- [PC]
        `ROM_DATA_SIZE'b1_000_1_000_0_0_0_0_0_0_000_0_0_0000_0,  // Rd <- Rs
        `ROM_DATA_SIZE'b1_000_0_000_1_0_0_1_0_0_000_0_0_0000_0,  // Rd <- IR
        `ROM_DATA_SIZE'b0_000_1_000_0_0_0_0_1_0_000_0_0_0000_0,

        /* Read Register select */
        `ROM_DATA_SIZE'b0_001_0_000_0_0_0_0_0_0_000_0_0_0000_0,  // A
        `ROM_DATA_SIZE'b0_010_0_000_0_0_0_0_0_0_000_0_0_0000_0,  // B
        `ROM_DATA_SIZE'b0_011_0_000_0_0_0_0_0_0_000_0_0_0000_0,  // C

        /* Write Register select */
        `ROM_DATA_SIZE'b0_000_0_001_0_0_0_0_0_0_000_0_0_0000_0,  // A
        `ROM_DATA_SIZE'b0_000_0_010_0_0_0_0_0_0_000_0_0_0000_0,  // B
        `ROM_DATA_SIZE'b0_000_0_011_0_0_0_0_0_0_000_0_0_0000_0,  // C

        `ROM_DATA_SIZE'b0_000_0_000_0_0_0_0_0_0_000_0_0_0000_0  // NOTHING
    };

    assign CTRL = memory[rom_addr] | memory[read_reg_addr] | memory[write_reg_addr];
endmodule

module Control #(
    parameter unsigned DATA_WIDTH = 16
) (
    input logic                      reset_n,
    input logic                      clk,
    input logic [DATA_WIDTH - 1 : 0] MDR,
    input logic [DATA_WIDTH - 1 : 0] IR,
    input logic                      Z_flag,
    input logic                      C_flag,

    output logic         Reg_Read,
    output logic [2 : 0] Reg_Read_Addr,
    output logic         Reg_Write,
    output logic [2 : 0] Reg_Write_Addr,

    output logic         Control_Read,
    output logic         Control_Write,
    output logic         Io_Read,
    output logic         IR_Read,
    output logic         IR_Write,
    output logic         MDR_Read,
    output logic [2 : 0] PC_Sel,

    output logic         ALU_In_1,
    output logic         ALU_In_2,
    output logic [3 : 0] ALU_Op_Sel,
    output logic         ALU_Out_Write
);

    logic [`ROM_ADDR_SIZE - 1 : 0] rom_addr;
    logic [`ROM_ADDR_SIZE - 1 : 0] read_reg_sel_addr;
    logic [`ROM_ADDR_SIZE - 1 : 0] write_reg_sel_addr;
    logic [`ROM_DATA_SIZE - 1 : 0] CTRL;

    logic [3 : 0] write_reg_sel, read_reg_sel;
    logic [7 : 0] instr;

    logic [7 : 0] state, next_state;

    ROM rom (
        .rom_addr          (rom_addr),
        .read_reg_sel_addr (read_reg_sel_addr),
        .write_reg_sel_addr(write_reg_sel_addr),
        .CTRL              (CTRL)
    );


    assign {instr, read_reg_sel, write_reg_sel} = MDR;

    assign {
        Reg_Read, Reg_Read_Addr, Reg_Write, Reg_Write_Addr,
        Control_Read, Control_Write, Io_Read, IR_Read, IR_Write, MDR_Read, PC_Sel,
        ALU_In_1, ALU_In_2, ALU_Op_Sel, ALU_Out_Write
    } = CTRL;

    always_ff @(posedge clk) begin
        if (!reset_n) begin
            state              <= 0;
            rom_addr           <= 0;
            read_reg_sel_addr  <= 0;
            write_reg_sel_addr <= 0;
        end
        state <= next_state;

        case (state)
            // Fetch Cycles
            0: begin
                case (instr)
                    `NOP: begin
                        rom_addr           <= 0;
                        read_reg_sel_addr  <= 0;
                        write_reg_sel_addr <= 0;
                        next_state         <= 0;
                    end
                    `MOV: begin
                        if (write_reg_sel == `IR_REG) begin
                            rom_addr           <= 2;
                            read_reg_sel_addr  <= 0;
                            write_reg_sel_addr <= 0;
                            next_state         <= 1;
                        end else begin
                            rom_addr           <= 1;
                            read_reg_sel_addr  <= read_reg_sel;
                            write_reg_sel_addr <= write_reg_sel;
                            next_state         <= 0;
                        end

                    end
                    default: begin
                        rom_addr           <= 0;
                        read_reg_sel_addr  <= 0;
                        write_reg_sel_addr <= 0;
                        next_state         <= 0;
                    end
                endcase
            end
            1: begin
                case (instr)
                    `MOV: begin
                        rom_addr           <= 3;
                        read_reg_sel_addr  <= read_reg_sel;
                        write_reg_sel_addr <= 0;
                        next_state         <= 0;
                    end
                    default: begin
                        rom_addr           <= 0;
                        read_reg_sel_addr  <= 0;
                        write_reg_sel_addr <= 0;
                        next_state         <= 0;
                    end
                endcase
            end
            // Execute Cycles

            default: begin
                rom_addr           <= 0;
                read_reg_sel_addr  <= 0;
                write_reg_sel_addr <= 0;
            end
        endcase
    end

endmodule

hardware/Register.sv
`timescale 1ns / 100ps

module Register #(
    parameter unsigned DATA_WIDTH = 16
) (
    input                       write,
    input                       read,
    input                       reset_n,
    input  [             2 : 0] addr_read,
    input  [             2 : 0] addr_write,
    input  [DATA_WIDTH - 1 : 0] data_write,
    output [DATA_WIDTH - 1 : 0] data_read,
    input                       clk
);

    logic [3 * DATA_WIDTH - 1 : 0] register;

    always @(posedge clk) begin
        if (!reset_n) register <= 'b0;
        else if (write) register[DATA_WIDTH*addr_write+:DATA_WIDTH] <= data_write;
    end

    assign data_read = read ? register[DATA_WIDTH*addr_read+:DATA_WIDTH] : {DATA_WIDTH{1'hz}};

endmodule

hardware/Alu.sv
`timescale 1ns / 100ps

module Alu #(
    parameter unsigned DATA_WIDTH = 16
) (
    input  logic [DATA_WIDTH - 1 : 0] A_reg,
    input  logic [DATA_WIDTH - 1 : 0] B_reg,
    input  logic [             3 : 0] op_select,
    output logic [DATA_WIDTH - 1 : 0] ALU_output,
    output bit                        Z_flag,
    output bit                        C_flag
);
    typedef enum {
        ADD = 1,
        SUB,
        DIV,
        MUL,
        SHIFT_R,
        SHIFT_L,
        JNZ,
        JZ,
        JNC,
        JC
    } alu_op_codes_e;

    logic [DATA_WIDTH : 0] result;

    always_comb begin
        case (op_select)
            ADD:     result = A_reg + B_reg;
            SUB:     result = A_reg - B_reg;
            DIV:     result = A_reg / B_reg;
            MUL:     result = A_reg * B_reg;
            SHIFT_L: result = A_reg << 1;
            SHIFT_R: result = A_reg >> 1;
            default: result = C_flag | A_reg;
        endcase

        ALU_output = result[DATA_WIDTH-1 : 0];
        C_flag     = result[DATA_WIDTH];
        Z_flag     = (result == 0) ? 1'b1 : 1'b0;
    end

endmodule

hardware/Processor.sv
`timescale 1ns / 100ps

module Processor #(
    parameter unsigned ADDR_WIDTH = 16,
    parameter unsigned DATA_WIDTH = 16
) (
    output logic [ADDR_WIDTH - 1:0] address,
    inout  logic [DATA_WIDTH - 1:0] data,
    output bit                      read_mem,
    output bit                      write_mem,
    input  bit                      reset_n,
    input  logic                    clk
);

    ////////////////////////  Declaration & Inittialization  ///////////////////////////////
    // Registers & flags
    reg [ADDR_WIDTH - 1 : 0] PC, SP;
    reg [DATA_WIDTH - 1 : 0] MDR, IR;
    logic Z_flag, C_flag;

    // control signals
    logic
        Reg_Write,
        Reg_Read,
        Control_Read,
        IR_Read,
        IR_Write,
        MDR_Read,
        Io_Read,
        Control_Write,
        ALU_In_1,
        ALU_In_2,
        ALU_Out_Write;
    logic [2:0] PC_Sel;
    logic [3:0] ALU_Op_Sel;
    logic [2 : 0] Reg_Read_Addr, Reg_Write_Addr;

    // interconnect wires & reg
    logic [DATA_WIDTH - 1 : 0] internal_databus;
    logic [ADDR_WIDTH - 1 : 0] next_pc;
    logic [DATA_WIDTH - 1 : 0] ALU_Src_A, ALU_Src_B, ALU_out;

    // ALU
    Alu alu (
        .A_reg     (ALU_Src_A),
        .B_reg     (ALU_Src_B),
        .op_select (ALU_Op_Sel),
        .ALU_output(ALU_out),
        .Z_flag    (Z_flag),
        .C_flag    (C_flag)
    );

    // Register File
    Register register (
        .write     (Reg_Write),
        .read      (Reg_Read),
        .reset_n   (reset_n),
        .clk       (clk),
        .data_read (internal_databus),
        .data_write(internal_databus),
        .addr_read (Reg_Read_Addr),
        .addr_write(Reg_Write_Addr)
    );

    // Control Unit
    Control control (
        .reset_n       (reset_n),
        .clk           (clk),
        .MDR           (MDR),
        .IR            (IR),
        .Reg_Write     (Reg_Write),
        .Reg_Read      (Reg_Read),
        .Control_Read  (Control_Read),
        .Control_Write (Control_Write),
        .Io_Read       (Io_Read),
        .IR_Read       (IR_Read),
        .IR_Write      (IR_Write),
        .MDR_Read      (MDR_Read),
        .PC_Sel        (PC_Sel),
        .Z_flag        (Z_flag),
        .C_flag        (C_flag),
        .ALU_In_1      (ALU_In_1),
        .ALU_In_2      (ALU_In_2),
        .ALU_Op_Sel    (ALU_Op_Sel),
        .ALU_Out_Write (ALU_Out_Write),
        .Reg_Read_Addr (Reg_Read_Addr),
        .Reg_Write_Addr(Reg_Write_Addr)
    );

    ////////////////////////////////////////////////////////////////////////////////////////

    ////////////////////////  Memory Access  ////////////////////////////

    // Read from memory (via pointer in register) to a register
    always_comb begin
        if (read_mem) assign internal_databus = data;
        else if (ALU_Out_Write) assign internal_databus = ALU_out;
        else if (IR_Write) assign internal_databus = IR;
        else assign internal_databus = {DATA_WIDTH{1'hz}};
    end

    // assign internal_databus = ALU_Out_Write ? ALU_out : read_mem ? data : {DATA_WIDTH{1'hz}};

    // Write to memory (via pointer in register) from a register
    assign data = write_mem ? internal_databus : {DATA_WIDTH{1'hz}};

    always_ff @(posedge clk) begin
        if (Control_Read) begin
            address  = Io_Read ? IR : PC;
            read_mem = 1;
            IR       = IR_Read ? internal_databus : {DATA_WIDTH{1'b0}};
            MDR      = MDR_Read ? internal_databus : {DATA_WIDTH{1'b0}};
        end else begin
            address  = {DATA_WIDTH{1'hz}};
            read_mem = 0;
        end

        if (Control_Write) begin
            address   = IR;
            write_mem = 1;
        end else begin
            address   = {DATA_WIDTH{1'hz}};
            write_mem = 0;
        end
    end

    //////////////////////////////////////////////////////////////////////

    ////////////////////////  ALU  ////////////////////////////

    always_comb begin
        case (ALU_In_1)
            1: ALU_Src_A = internal_databus;
            default: begin
                ALU_Src_A = {DATA_WIDTH{1'b0}};
            end
        endcase
        case (ALU_In_2)
            0: ALU_Src_B = internal_databus;
            1: ALU_Src_B = IR;
            default: begin
                ALU_Src_B = {DATA_WIDTH{1'b0}};
            end
        endcase
    end

    ///////////////////////////////////////////////////////////

    ////////////////////////  CPU reset Program Counter ////////////////////////////

    always_ff @(posedge clk) begin
        case (PC_Sel)
            0: next_pc <= PC + 1'b1;
            1: next_pc <= Z_flag ? IR : PC + 1'b1;
            2: next_pc <= (!Z_flag) ? IR : PC + 1'b1;
            3: next_pc <= (C_flag) ? IR : PC + 1'b1;
            4: next_pc <= (!C_flag) ? IR : PC + 1'b1;
            default: begin
            end
        endcase
    end

    always @(posedge clk) begin
        if (!reset_n) PC <= {ADDR_WIDTH{1'b0}};
        else PC <= next_pc;

    end

    //////////////////////////////////////////////////////////////////////


endmodule

hardware/Memory.sv
`timescale 1ns / 100ps

module Memory #(
    parameter unsigned ADDR_WIDTH = 16,
    parameter unsigned DATA_WIDTH = 16,
    parameter unsigned DEPTH = 2 ** ADDR_WIDTH
) (
    input bit                    write,
    input bit                    read,
    input logic                  clk,
    input logic [ADDR_WIDTH-1:0] addr,
    inout logic [DATA_WIDTH-1:0] data
);

    logic [DATA_WIDTH-1:0] tmp_data;
    logic [DATA_WIDTH-1:0] mem[5];

    always @(posedge clk) begin
        if (write) mem[addr] <= data;
    end

    always @(posedge clk) begin
        if (read) tmp_data <= mem[addr];
    end

    assign data = (!write && read) ? tmp_data : {DATA_WIDTH{1'hz}};

endmodule

hardware/test_benches/Processor_tb.sv
`timescale 1ns / 100ps

module Processor_tb;
    parameter unsigned ADDR_WIDTH = 16;
    parameter unsigned DATA_WIDTH = 16;


    logic clk, read, write, reset_n;
    logic [ADDR_WIDTH-1:0] addr;
    logic [DATA_WIDTH-1:0] data;

    Memory memory (
        .write(write),
        .read (read),
        .clk  (clk),
        .addr (addr),
        .data (data)
    );

    Processor u0 (
        .address  (addr),
        .data     (data),
        .read_mem (read),
        .write_mem(write),
        .clk      (clk),
        .reset_n  (reset_n)
    );



    always #1 clk = ~clk;

    initial begin
        #1 reset_n = 0;
        $readmemh("memory.hex", memory.mem, 0, 4);
        #3 reset_n = 1;
        #100 $finish;
    end
    initial begin
        $dumpfile("waveform.vcd");
        $dumpvars;
    end

endmodule

hardware/test_benches/waveform.vcd
$version Generated by VerilatedVcd $end
$timescale 100ps $end
 $scope module TOP $end
  $scope module Processor_tb $end
   $var wire 32 c ADDR_WIDTH [31:0] $end
   $var wire 32 c DATA_WIDTH [31:0] $end
   $var wire 1 T clk $end
   $var wire 1 . read $end
   $var wire 1 / write $end
   $var wire 1 U reset_n $end
   $var wire 16 0 addr [15:0] $end
   $var wire 16 V data [15:0] $end
   $scope module memory $end
    $var wire 32 c ADDR_WIDTH [31:0] $end
    $var wire 32 c DATA_WIDTH [31:0] $end
    $var wire 32 d DEPTH [31:0] $end
    $var wire 1 / write $end
    $var wire 1 . read $end
    $var wire 1 T clk $end
    $var wire 16 0 addr [15:0] $end
    $var wire 16 V data [15:0] $end
    $var wire 16 2 tmp_data [15:0] $end
    $var wire 16 W mem[0] [15:0] $end
    $var wire 16 X mem[1] [15:0] $end
    $var wire 16 Y mem[2] [15:0] $end
    $var wire 16 Z mem[3] [15:0] $end
    $var wire 16 [ mem[4] [15:0] $end
   $upscope $end
   $scope module u0 $end
    $var wire 32 c ADDR_WIDTH [31:0] $end
    $var wire 32 c DATA_WIDTH [31:0] $end
    $var wire 16 0 address [15:0] $end
    $var wire 16 V data [15:0] $end
    $var wire 1 . read_mem $end
    $var wire 1 / write_mem $end
    $var wire 1 U reset_n $end
    $var wire 1 T clk $end
    $var wire 16 3 PC [15:0] $end
    $var wire 16 e SP [15:0] $end
    $var wire 16 4 MDR [15:0] $end
    $var wire 16 1 IR [15:0] $end
    $var wire 1 \ Z_flag $end
    $var wire 1 ] C_flag $end
    $var wire 1 5 Reg_Write $end
    $var wire 1 6 Reg_Read $end
    $var wire 1 7 Control_Read $end
    $var wire 1 8 IR_Read $end
    $var wire 1 9 IR_Write $end
    $var wire 1 : MDR_Read $end
    $var wire 1 ; Io_Read $end
    $var wire 1 < Control_Write $end
    $var wire 1 = ALU_In_1 $end
    $var wire 1 > ALU_In_2 $end
    $var wire 1 ? ALU_Out_Write $end
    $var wire 3 @ PC_Sel [2:0] $end
    $var wire 4 A ALU_Op_Sel [3:0] $end
    $var wire 3 B Reg_Read_Addr [2:0] $end
    $var wire 3 C Reg_Write_Addr [2:0] $end
    $var wire 16 ^ internal_databus [15:0] $end
    $var wire 16 D next_pc [15:0] $end
    $var wire 16 _ ALU_Src_A [15:0] $end
    $var wire 16 ` ALU_Src_B [15:0] $end
    $var wire 16 a ALU_out [15:0] $end
    $scope module alu $end
     $var wire 32 c DATA_WIDTH [31:0] $end
     $var wire 16 _ A_reg [15:0] $end
     $var wire 16 ` B_reg [15:0] $end
     $var wire 4 A op_select [3:0] $end
     $var wire 16 a ALU_output [15:0] $end
     $var wire 1 \ Z_flag $end
     $var wire 1 ] C_flag $end
     $var wire 17 b result [16:0] $end
    $upscope $end
    $scope module control $end
     $var wire 32 c DATA_WIDTH [31:0] $end
     $var wire 1 U reset_n $end
     $var wire 1 T clk $end
     $var wire 16 4 MDR [15:0] $end
     $var wire 16 1 IR [15:0] $end
     $var wire 1 \ Z_flag $end
     $var wire 1 ] C_flag $end
     $var wire 1 6 Reg_Read $end
     $var wire 3 B Reg_Read_Addr [2:0] $end
     $var wire 1 5 Reg_Write $end
     $var wire 3 C Reg_Write_Addr [2:0] $end
     $var wire 1 7 Control_Read $end
     $var wire 1 < Control_Write $end
     $var wire 1 ; Io_Read $end
     $var wire 1 8 IR_Read $end
     $var wire 1 9 IR_Write $end
     $var wire 1 : MDR_Read $end
     $var wire 3 @ PC_Sel [2:0] $end
     $var wire 1 = ALU_In_1 $end
     $var wire 1 > ALU_In_2 $end
     $var wire 4 A ALU_Op_Sel [3:0] $end
     $var wire 1 ? ALU_Out_Write $end
     $var wire 32 E rom_addr [31:0] $end
     $var wire 32 F read_reg_sel_addr [31:0] $end
     $var wire 32 G write_reg_sel_addr [31:0] $end
     $var wire 24 H CTRL [23:0] $end
     $var wire 4 I write_reg_sel [3:0] $end
     $var wire 4 J read_reg_sel [3:0] $end
     $var wire 8 K instr [7:0] $end
     $var wire 8 L state [7:0] $end
     $var wire 8 M next_state [7:0] $end
     $scope module rom $end
      $var wire 32 E rom_addr [31:0] $end
      $var wire 3 N read_reg_sel_addr [2:0] $end
      $var wire 3 O write_reg_sel_addr [2:0] $end
      $var wire 24 H CTRL [23:0] $end
      $var wire 24 P read_reg_addr [23:0] $end
      $var wire 24 Q write_reg_addr [23:0] $end
      $var wire 24 # memory[0] [23:0] $end
      $var wire 24 $ memory[1] [23:0] $end
      $var wire 24 % memory[2] [23:0] $end
      $var wire 24 & memory[3] [23:0] $end
      $var wire 24 ' memory[4] [23:0] $end
      $var wire 24 ( memory[5] [23:0] $end
      $var wire 24 ) memory[6] [23:0] $end
      $var wire 24 * memory[7] [23:0] $end
      $var wire 24 + memory[8] [23:0] $end
      $var wire 24 , memory[9] [23:0] $end
      $var wire 24 - memory[10] [23:0] $end
     $upscope $end
    $upscope $end
    $scope module register $end
     $var wire 32 c DATA_WIDTH [31:0] $end
     $var wire 1 5 write $end
     $var wire 1 6 read $end
     $var wire 1 U reset_n $end
     $var wire 3 B addr_read [2:0] $end
     $var wire 3 C addr_write [2:0] $end
     $var wire 16 ^ data_write [15:0] $end
     $var wire 16 ^ data_read [15:0] $end
     $var wire 1 T clk $end
     $var wire 48 R register [47:0] $end
    $upscope $end
   $upscope $end
  $upscope $end
 $upscope $end
$enddefinitions $end


#0
b000000001000010000000000 #
b100010000000000000000000 $
b100000001001000000000000 %
b000010000000100000000000 &
b000100000000000000000000 '
b001000000000000000000000 (
b001100000000000000000000 )
b000000010000000000000000 *
b000000100000000000000000 +
b000000110000000000000000 ,
b000000000000000000000000 -
0.
0/
b0000000000000000 0
b0000000000000000 1
b0000000000000000 2
b0000000000000000 3
b0000000000000000 4
15
06
17
08
19
1:
0;
0<
0=
0>
0?
b000 @
b0000 A
b011 B
b000 C
b0000000000000000 D
b00000000000000000000000000000000 E
b00000000000000000000000000000000 F
b00000000000000000000000000000000 G
b001110001000110000000000 H
b0000 I
b0000 J
b00000000 K
b00000000 L
b00000000 M
b000 N
b000 O
b000000000000000000000011 P
b000000000000000000000110 Q
b000000000000000000000000000000000000000000000000 R
0T
0U
b0000000000000000 V
b0000000000000000 W
b0000000000000000 X
b0000000000000000 Y
b0000000000000000 Z
b0000000000000000 [
1\
0]
b0000000000000000 ^
b0000000000000000 _
b0000000000000000 `
b0000000000000000 a
b00000000000000000 b
b00000000000000000000000000010000 c
b00000000000000010000000000000000 d
b0000000000000000 e
#10
1.
b0000000000000001 D
1T
b0000000100100100 X
b1100101011111110 Y
b0000000100010010 Z
b1111111111111111 [
#20
0T
#30
1T
#40
0T
1U
#50
b0000000000000001 3
1T
#60
0T
#70
b0000000000000001 0
b0000000100100100 2
b0000000000000010 D
1T
b0000000100100100 V
b0000000100100100 ^
b0000000100100100 `
#80
0T
#90
b0000000000000010 3
b0000000100100100 4
16
18
0:
b00000000000000000000000000000010 E
b101110001001100000000000 H
b0100 I
b0010 J
b00000001 K
b00000001 M
b000000000000000000000000000000000000000100100100 R
1T
#100
0T
#110
b0000000000000010 0
b0000000100100100 1
b1100101011111110 2
b0000000000000000 4
06
08
1:
b0000000000000011 D
b00000000000000000000000000000000 E
b001110001000110000000000 H
b0000 I
b0000 J
b00000000 K
b00000001 L
b00000000 M
1T
b1100101011111110 V
b1100101011111110 ^
b1100101011111110 `
#120
0T
#130
b0000000000000000 1
b0000000000000011 3
b1100101011111110 4
b1110 I
b1111 J
b11001010 K
b00000000 L
b000000000000000000000000000000001100101011111110 R
1T
#140
0T
#150
b0000000000000011 0
b0000000100010010 2
b0000000000000100 D
1T
b0000000100010010 V
b0000000100010010 ^
b0000000100010010 `
#160
0T
#170
b0000000000000100 3
b0000000100010010 4
16
07
09
0:
b001 B
b010 C
b00000000000000000000000000000001 E
b00000000000000000000000000000001 F
b00000000000000000000000000000010 G
b100110100000000000000000 H
b0010 I
b0001 J
b00000001 K
b001 N
b010 O
b000000000000000000000100 P
b000000000000000000001000 Q
b000000000000000000000000000000000000000100010010 R
1T
#180
0T
#190
0.
b0000000000000101 D
1T
b0000000000000000 V
b0000000000000000 ^
b0000000000000000 `
#200
0T
#210
b0000000000000101 3
1T
#220
0T
#230
b0000000000000110 D
1T
#240
0T
#250
b0000000000000110 3
1T
#260
0T
#270
b0000000000000111 D
1T
#280
0T
#290
b0000000000000111 3
1T
#300
0T
#310
b0000000000001000 D
1T
#320
0T
#330
b0000000000001000 3
1T
#340
0T
#350
b0000000000001001 D
1T
#360
0T
#370
b0000000000001001 3
1T
#380
0T
#390
b0000000000001010 D
1T
#400
0T
#410
b0000000000001010 3
1T
#420
0T
#430
b0000000000001011 D
1T
#440
0T
#450
b0000000000001011 3
1T
#460
0T
#470
b0000000000001100 D
1T
#480
0T
#490
b0000000000001100 3
1T
#500
0T
#510
b0000000000001101 D
1T
#520
0T
#530
b0000000000001101 3
1T
#540
0T
#550
b0000000000001110 D
1T
#560
0T
#570
b0000000000001110 3
1T
#580
0T
#590
b0000000000001111 D
1T
#600
0T
#610
b0000000000001111 3
1T
#620
0T
#630
b0000000000010000 D
1T
#640
0T
#650
b0000000000010000 3
1T
#660
0T
#670
b0000000000010001 D
1T
#680
0T
#690
b0000000000010001 3
1T
#700
0T
#710
b0000000000010010 D
1T
#720
0T
#730
b0000000000010010 3
1T
#740
0T
#750
b0000000000010011 D
1T
#760
0T
#770
b0000000000010011 3
1T
#780
0T
#790
b0000000000010100 D
1T
#800
0T
#810
b0000000000010100 3
1T
#820
0T
#830
b0000000000010101 D
1T
#840
0T
#850
b0000000000010101 3
1T
#860
0T
#870
b0000000000010110 D
1T
#880
0T
#890
b0000000000010110 3
1T
#900
0T
#910
b0000000000010111 D
1T
#920
0T
#930
b0000000000010111 3
1T
#940
0T
#950
b0000000000011000 D
1T
#960
0T
#970
b0000000000011000 3
1T
#980
0T
#990
b0000000000011001 D
1T
#1000
0T
#1010
b0000000000011001 3
1T
#1020
0T
#1030
b0000000000011010 D
1T
