hardware/opcode.sv
`define NOP 8'b0000_0000
`define HLT 8'b1111_1111

`define MOV 8'b0000_0001
`define LDA 8'b0000_0010
`define STA 8'b0000_0011

`define ADD 8'b0000_0100
`define SUB 8'b0000_0101
`define MUL 8'b0000_0110
`define DIV 8'b0000_0111

`define AND 8'b0000_1000
`define OR 8'b0000_1001
`define XOR 8'b0000_1010
`define NOT 8'b0000_1011
`define RR 8'b0000_1100

`define PUSH 8'b0000_1101
`define POP 8'b0000_1110

`define JUMP 8'b1000_0000
`define CALL 8'b1010_0000
`define RET 8'b1011_0000

`define NO_REG 3'b000
`define B_REG 3'b001
`define C_REG 3'b010
`define D_REG 3'b001
`define E_REG 3'b100
`define PC_REG 3'b101
`define SP_REG 3'b110
`define A_REG 3'b111

`define NO_OP 4'b0000
`define ADD_OP 4'b0001
`define SUB_OP 4'b0010
`define MUL_OP 4'b0011
`define DIV_OP 4'b0100
`define AND_OP 4'b1000
`define OR_OP 4'b1001
`define XOR_OP 4'b1010
`define NOT_OP 4'b1011
`define RRS_OP 4'b1100
`define RRC_OP 4'b1101
`define LLS_OP 4'b1110
`define LLC_OP 4'b1111

hardware/Control.sv
`include "opcode.sv"

`timescale 1ns / 100ps
`define ROM_ADDR_SIZE 32
`define ROM_DATA_SIZE 24
`define ROM_NUM_INST_SIZE 11

module ROM (
    input  logic [`ROM_ADDR_SIZE - 1 : 0] rom_addr,
    input  logic [                 3 : 0] param_1_addr,
    input  logic [                 3 : 0] param_2_addr,
    output logic [`ROM_DATA_SIZE - 1 : 0] CTRL
);

    logic [3 : 0] read_reg_addr = (param_1_addr != 4'h0) ? (`ROM_NUM_INST_SIZE - 1) - 3 - param_1_addr : (`ROM_NUM_INST_SIZE - 1);
    logic [3 : 0] write_reg_addr = (param_2_addr != 4'h0) ? (`ROM_NUM_INST_SIZE - 1) - param_2_addr : (`ROM_NUM_INST_SIZE - 1);
    // localparam logic [`ROM_DATA_SIZE * (`ROM_NUM_INST_SIZE + 1) - 1:0] memory = {
    localparam logic [`ROM_DATA_SIZE - 1:0] memory[`ROM_NUM_INST_SIZE] = {
        /*
         * Reg_Read, Reg_Read_Addr[2:0], Reg_Write, Reg_Write_Addr[2:0],
         * Control_Read, Control_Write, Io_Read, IR_Read, IR_Write, MDR_Read, PC_Sel[2:0],
         * ALU_In_1, ALU_In_2, ALU_Op_Sel[3:0], ALU_Out_Write
         */

        `ROM_DATA_SIZE'b0_000_0_000_1_0_0_0_0_1_001_0_0_0000_0,  // MDR <- [PC]
        `ROM_DATA_SIZE'b1_000_1_000_0_0_0_0_0_0_001_0_0_0000_0,  // Rd <- Rs
        `ROM_DATA_SIZE'b1_000_0_000_1_0_0_1_0_0_001_0_0_0000_0,  // IR <- data
        `ROM_DATA_SIZE'b0_000_1_000_0_0_0_0_1_0_001_0_0_0000_0,  // Rd <- IR

        /* Read Register select */
        `ROM_DATA_SIZE'b0_011_0_000_0_0_0_0_0_0_000_0_0_0000_0,  // C
        `ROM_DATA_SIZE'b0_010_0_000_0_0_0_0_0_0_000_0_0_0000_0,  // B
        `ROM_DATA_SIZE'b0_001_0_000_0_0_0_0_0_0_000_0_0_0000_0,  // A

        /* Write Register select */
        `ROM_DATA_SIZE'b0_000_0_011_0_0_0_0_0_0_000_0_0_0000_0,  // C
        `ROM_DATA_SIZE'b0_000_0_010_0_0_0_0_0_0_000_0_0_0000_0,  // B
        `ROM_DATA_SIZE'b0_000_0_001_0_0_0_0_0_0_000_0_0_0000_0,  // A

        `ROM_DATA_SIZE'b0_000_0_000_0_0_0_0_0_0_000_0_0_0000_0  // NOTHING
    };

    assign CTRL = memory[rom_addr] | memory[read_reg_addr] | memory[write_reg_addr];
endmodule

module Control #(
    parameter unsigned DATA_WIDTH = 16
) (
    input logic                      reset_n,
    input logic                      clk,
    input logic [DATA_WIDTH - 1 : 0] MDR,
    input logic                      Z_flag,
    input logic                      C_flag,

    output logic         Reg_Read,
    output logic [2 : 0] Reg_Read_Addr,
    output logic         Reg_Write,
    output logic [2 : 0] Reg_Write_Addr,

    output logic         Control_Read,
    output logic         Control_Write,
    output logic         Io_Read,
    output logic         IR_Read,
    output logic         IR_Write,
    output logic         MDR_Read,
    output logic [2 : 0] PC_Sel,

    output logic         ALU_In_1,
    output logic         ALU_In_2,
    output logic [3 : 0] ALU_Op_Sel,
    output logic         ALU_Out_Write
);

    logic [`ROM_ADDR_SIZE - 1 : 0] rom_addr;
    logic [`ROM_DATA_SIZE - 1 : 0] CTRL;

    logic [3 : 0] param_2, param_1, param_2_addr, param_1_addr;
    logic [7 : 0] instr;

    logic [7 : 0] state, next_state;

    ROM rom (
        .rom_addr    (rom_addr),
        .param_1_addr(param_1_addr),
        .param_2_addr(param_2_addr),
        .CTRL        (CTRL)
    );

    initial begin
        state      = 'hFF;
        next_state = 0;
        CTRL       = 0;
    end


    assign {instr, param_1, param_2} = MDR;

    assign {
        Reg_Read, Reg_Read_Addr, Reg_Write, Reg_Write_Addr,
        Control_Read, Control_Write, Io_Read, IR_Read, IR_Write, MDR_Read, PC_Sel,
        ALU_In_1, ALU_In_2, ALU_Op_Sel, ALU_Out_Write
    } = CTRL;

    always_ff @(posedge clk) begin
        if (!reset_n) state <= 0;
        else state <= next_state;
        case (state)
            0: begin
                case (instr)
                    `NOP: begin
                        rom_addr     <= 0;
                        param_1_addr <= 0;
                        param_2_addr <= 0;
                        next_state   <= 0;
                    end
                    `MOV: begin
                        if (param_2 == {1'b0, `IR_REG}) begin
                            rom_addr     <= 1;
                            param_1_addr <= 0;
                            param_2_addr <= 0;
                            next_state   <= 2;
                        end else begin
                            rom_addr     <= 1;
                            param_1_addr <= param_1;
                            param_2_addr <= param_2;
                            next_state   <= 0;
                        end

                    end
                    default: begin
                        rom_addr     <= 0;
                        param_1_addr <= 0;
                        param_2_addr <= 0;
                        next_state   <= 0;
                    end
                endcase
            end
            1: begin
                case (instr)
                    `MOV: begin
                        rom_addr     <= 3;
                        param_1_addr <= param_1;
                        param_2_addr <= 0;
                        next_state   <= 0;
                    end
                    default: begin
                        rom_addr     <= 0;
                        param_1_addr <= 0;
                        param_2_addr <= 0;
                        next_state   <= 0;
                    end
                endcase
            end
            // Execute Cycles

            default: begin
                rom_addr     <= 0;
                param_1_addr <= 0;
                param_2_addr <= 0;
            end
        endcase
    end

endmodule

hardware/test_benches/Control_tb.sv
`timescale 1ns / 100ps

module Control_tb;

    parameter unsigned ADDR_WIDTH = 16;
    parameter unsigned DATA_WIDTH = 16;

    logic clk, reset_n, Z_flag, C_flag;
    logic [DATA_WIDTH - 1 : 0] MDR;

    Control u0 (
        .reset_n(reset_n),
        .clk    (clk),
        .MDR    (MDR),
        .Z_flag (Z_flag),
        .C_flag (C_flag)
    );

    always #1 clk = ~clk;

    initial begin
        clk     = 0;
        Z_flag  = 0;
        C_flag  = 0;
        reset_n = 0;
        MDR     = 'hFFFF;
        #0.5 reset_n = 1;

        #2.5 MDR = 'h0000;
        #2 MDR = 'h0124;
        // #2 MDR = 'hCAFE;
        #4 MDR = 'hFFFF;
        #2 MDR = 'h0000;

        #10 $finish;
    end

    initial begin
        $dumpfile("waveform.vcd");
        $dumpvars;
    end

endmodule

hardware/test_benches/waveform.vcd
$version Generated by VerilatedVcd $end
$timescale 100ps $end
 $scope module TOP $end
  $scope module Control_tb $end
   $var wire 32 B ADDR_WIDTH [31:0] $end
   $var wire 32 B DATA_WIDTH [31:0] $end
   $var wire 1 A clk $end
   $var wire 1 % reset_n $end
   $var wire 1 & Z_flag $end
   $var wire 1 ' C_flag $end
   $var wire 16 ( MDR [15:0] $end
   $scope module u0 $end
    $var wire 32 B DATA_WIDTH [31:0] $end
    $var wire 1 % reset_n $end
    $var wire 1 A clk $end
    $var wire 16 ( MDR [15:0] $end
    $var wire 1 & Z_flag $end
    $var wire 1 ' C_flag $end
    $var wire 1 , Reg_Read $end
    $var wire 3 - Reg_Read_Addr [2:0] $end
    $var wire 1 . Reg_Write $end
    $var wire 3 / Reg_Write_Addr [2:0] $end
    $var wire 1 0 Control_Read $end
    $var wire 1 1 Control_Write $end
    $var wire 1 2 Io_Read $end
    $var wire 1 3 IR_Read $end
    $var wire 1 4 IR_Write $end
    $var wire 1 5 MDR_Read $end
    $var wire 3 6 PC_Sel [2:0] $end
    $var wire 1 7 ALU_In_1 $end
    $var wire 1 8 ALU_In_2 $end
    $var wire 4 9 ALU_Op_Sel [3:0] $end
    $var wire 1 : ALU_Out_Write $end
    $var wire 32 > rom_addr [31:0] $end
    $var wire 24 ; CTRL [23:0] $end
    $var wire 4 ) param_2 [3:0] $end
    $var wire 4 * param_1 [3:0] $end
    $var wire 4 ? param_2_addr [3:0] $end
    $var wire 4 @ param_1_addr [3:0] $end
    $var wire 8 + instr [7:0] $end
    $var wire 8 < state [7:0] $end
    $var wire 8 = next_state [7:0] $end
    $scope module rom $end
     $var wire 32 > rom_addr [31:0] $end
     $var wire 4 @ param_1_addr [3:0] $end
     $var wire 4 ? param_2_addr [3:0] $end
     $var wire 24 ; CTRL [23:0] $end
     $var wire 4 # read_reg_addr [3:0] $end
     $var wire 4 $ write_reg_addr [3:0] $end
     $var wire 24 C memory[0] [23:0] $end
     $var wire 24 D memory[1] [23:0] $end
     $var wire 24 E memory[2] [23:0] $end
     $var wire 24 F memory[3] [23:0] $end
     $var wire 24 G memory[4] [23:0] $end
     $var wire 24 H memory[5] [23:0] $end
     $var wire 24 I memory[6] [23:0] $end
     $var wire 24 J memory[7] [23:0] $end
     $var wire 24 K memory[8] [23:0] $end
     $var wire 24 L memory[9] [23:0] $end
     $var wire 24 M memory[10] [23:0] $end
    $upscope $end
   $upscope $end
  $upscope $end
 $upscope $end
$enddefinitions $end


#0
b1010 #
b1010 $
0%
0&
0'
b1111111111111111 (
b1111 )
b1111 *
b11111111 +
0,
b000 -
0.
b000 /
10
01
02
03
04
15
b001 6
07
08
b0000 9
0:
b000000001000010010000000 ;
b11111111 <
b00000000 =
b00000000000000000000000000000000 >
b0000 ?
b0000 @
0A
b00000000000000000000000000010000 B
b000000001000010010000000 C
b100010000000000010000000 D
b100000001001000010000000 E
b000010000000100010000000 F
b001100000000000000000000 G
b001000000000000000000000 H
b000100000000000000000000 I
b000000110000000000000000 J
b000000100000000000000000 K
b000000010000000000000000 L
b000000000000000000000000 M
#5
1%
#10
b00000000 <
1A
#20
0A
#30
b0000000000000000 (
b0000 )
b0000 *
b00000000 +
1A
#40
0A
#50
b0000000100100100 (
b0100 )
b0010 *
b00000001 +
1,
1.
00
05
b100010000000000010000000 ;
b00000010 =
b00000000000000000000000000000001 >
1A
#60
0A
#70
b00000010 <
1A
#80
0A
#90
b1111111111111111 (
b1111 )
b1111 *
b11111111 +
0,
0.
10
15
b000000001000010010000000 ;
b00000000000000000000000000000000 >
1A
#100
0A
#110
b0000000000000000 (
b0000 )
b0000 *
b00000000 +
1A
