hardware/opcode.sv
`define NOP 8'b0000_0000
`define HLT 8'b1111_1111

`define MOV 8'b0000_0001
`define LDA 8'b0000_0010
`define STA 8'b0000_0011

`define ADD 8'b0000_0100
`define SUB 8'b0000_0101
`define MUL 8'b0000_0110
`define DIV 8'b0000_0111

`define AND 8'b0000_1000
`define OR 8'b0000_1001
`define XOR 8'b0000_1010
`define NOT 8'b0000_1011
`define RR 8'b0000_1100

`define PUSH 8'b0000_1101
`define POP 8'b0000_1110

`define JUMP 8'b1000_0000
`define CALL 8'b1010_0000
`define RET 8'b1011_0000

`define NO_REG 3'b000
`define B_REG 3'b001
`define C_REG 3'b010
`define D_REG 3'b001
`define E_REG 3'b100
`define PC_REG 3'b101
`define SP_REG 3'b110
`define A_REG 3'b111

`define NO_OP 4'b0000
`define ADD_OP 4'b0001
`define SUB_OP 4'b0010
`define MUL_OP 4'b0011
`define DIV_OP 4'b0100
`define AND_OP 4'b1000
`define OR_OP 4'b1001
`define XOR_OP 4'b1010
`define NOT_OP 4'b1011
`define RRS_OP 4'b1100
`define RRC_OP 4'b1101
`define LLS_OP 4'b1110
`define LLC_OP 4'b1111

hardware/Control.sv
`include "opcode.sv"

`timescale 1ns / 100ps
`define ROM_ADDR_SIZE 4
`define ROM_DATA_SIZE 24
`define ROM_NUM_INST_SIZE 11
`define ROM_NOTHING `ROM_NUM_INST_SIZE - 1
`define RESET 255
`define STATE_END 0

module ROM (
    input  logic [`ROM_ADDR_SIZE - 1 : 0] rom_addr,
    input  logic [                 3 : 0] read_addr,
    input  logic [                 3 : 0] write_addr,
    output logic [`ROM_DATA_SIZE - 1 : 0] CTRL
);

    logic [3 : 0] read_reg_addr, write_reg_addr;
    always_comb begin
        read_reg_addr  = (read_addr != 4'h0) ? (`ROM_NOTHING - 3 - read_addr) : `ROM_NOTHING;
        write_reg_addr = (write_addr != 4'h0) ? (`ROM_NOTHING - write_addr) : `ROM_NOTHING;
    end
    // localparam logic [`ROM_DATA_SIZE * (`ROM_NUM_INST_SIZE + 1) - 1:0] memory = {
    localparam logic [`ROM_DATA_SIZE - 1:0] memory[`ROM_NUM_INST_SIZE] = {
        /*
         * Reg_Read, Reg_Read_Addr[2:0], Reg_Write, Reg_Write_Addr[2:0],
         * Control_Read, Control_Write, Io_Read, IR_Write, IR_Read, MDR_Read, PC_Sel[2:0],
         * ALU_In_1, ALU_In_2, ALU_Op_Sel[3:0], ALU_Out_Write
         */

        // Fetch
        `ROM_DATA_SIZE'b0_000_0_000_1_0_0_0_0_1_001_0_0_0000_0,  // MDR <- [PC]

        // Decode & Execute
        `ROM_DATA_SIZE'b1_000_1_000_0_0_0_0_0_0_000_0_0_0000_0,  // Rd <- Rs
        `ROM_DATA_SIZE'b0_000_0_000_1_0_0_1_0_0_001_0_0_0000_0,  // IR <- data
        `ROM_DATA_SIZE'b0_000_1_000_0_0_0_0_1_0_000_0_0_0000_0,  // Rd <- IR

        /* Read Register select */
        `ROM_DATA_SIZE'b0_011_0_000_0_0_0_0_0_0_000_0_0_0000_0,  // C
        `ROM_DATA_SIZE'b0_010_0_000_0_0_0_0_0_0_000_0_0_0000_0,  // B
        `ROM_DATA_SIZE'b0_001_0_000_0_0_0_0_0_0_000_0_0_0000_0,  // A
        /* Write Register select */
        `ROM_DATA_SIZE'b0_000_0_011_0_0_0_0_0_0_000_0_0_0000_0,  // C
        `ROM_DATA_SIZE'b0_000_0_010_0_0_0_0_0_0_000_0_0_0000_0,  // B
        `ROM_DATA_SIZE'b0_000_0_001_0_0_0_0_0_0_000_0_0_0000_0,  // A

        // END
        `ROM_DATA_SIZE'b0_000_0_000_0_0_0_0_0_0_000_0_0_0000_0  // Nothing
    };

    assign CTRL = memory[rom_addr] | memory[read_reg_addr] | memory[write_reg_addr];
    // assign CTRL = memory[`ROM_DATA_SIZE*rom_addr+:`ROM_DATA_SIZE] | memory[`ROM_DATA_SIZE*read_reg_addr+:`ROM_DATA_SIZE] | memory[`ROM_DATA_SIZE*write_reg_addr+:`ROM_DATA_SIZE];
endmodule

module Control #(
    parameter unsigned DATA_WIDTH = 16
) (
    input logic                      reset_n,
    input logic                      clk,
    input logic [DATA_WIDTH - 1 : 0] MDR,
    input logic                      Z_flag,
    input logic                      C_flag,

    output logic         Reg_Read,
    output logic [2 : 0] Reg_Read_Addr,
    output logic         Reg_Write,
    output logic [2 : 0] Reg_Write_Addr,

    output logic         Control_Read,
    output logic         Control_Write,
    output logic         Io_Read,
    output logic         IR_Write,
    output logic         IR_Read,
    output logic         MDR_Read,
    output logic [2 : 0] PC_Sel,

    output logic         ALU_In_1,
    output logic         ALU_In_2,
    output logic [3 : 0] ALU_Op_Sel,
    output logic         ALU_Out_Write
);

    logic [`ROM_ADDR_SIZE - 1 : 0] rom_addr;
    logic [`ROM_DATA_SIZE - 1 : 0] CTRL;

    logic [3 : 0] param_2, param_1, write_addr, read_addr;
    logic [7 : 0] instr;

    logic [7 : 0] state, next_state;

    ROM rom (
        .rom_addr  (rom_addr),
        .read_addr (read_addr),
        .write_addr(write_addr),
        .CTRL      (CTRL)
    );


    assign {instr, param_1, param_2} = MDR;

    assign {
        Reg_Read, Reg_Read_Addr, Reg_Write, Reg_Write_Addr,
        Control_Read, Control_Write, Io_Read, IR_Write, IR_Read, MDR_Read, PC_Sel,
        ALU_In_1, ALU_In_2, ALU_Op_Sel, ALU_Out_Write
    } = CTRL;

    always_ff @(posedge clk) begin
        if (!reset_n) state <= 'hFF;
        else state <= next_state;
    end

    always_comb begin
        case (state)
            // Fetch
            0: begin
                rom_addr   = 0;
                write_addr = 0;
                read_addr  = 0;
                next_state = 1;
            end

            // Decode & Execute
            1: begin
                case (instr)

                    `NOP: begin
                        rom_addr   = `ROM_NOTHING;
                        write_addr = 0;
                        read_addr  = 0;
                        next_state = `STATE_END;
                    end

                    `MOV: begin
                        if (param_2 == {1'b0, `IR_REG}) begin
                            rom_addr   = 2;
                            write_addr = 0;
                            read_addr  = 0;
                            next_state = 2;
                        end else begin
                            rom_addr   = 1;
                            write_addr = param_1;
                            read_addr  = param_2;
                            next_state = `STATE_END;
                        end
                    end

                    default: begin
                        rom_addr   = `ROM_NOTHING;
                        write_addr = 0;
                        read_addr  = 0;
                        next_state = `STATE_END;
                    end
                endcase
            end
            2: begin
                case (instr)

                    `MOV: begin
                        rom_addr   = 3;
                        write_addr = param_1;
                        read_addr  = 0;
                        next_state = `STATE_END;
                    end

                    default: begin
                        rom_addr   = `ROM_NOTHING;
                        write_addr = 0;
                        read_addr  = 0;
                        next_state = `STATE_END;
                    end
                endcase
            end

            // End / Reset Cycle
            `RESET: begin
                rom_addr   = `ROM_NOTHING;
                write_addr = 0;
                read_addr  = 0;
                next_state = 0;
            end

            default: begin
            end
        endcase
    end

endmodule

hardware/Register.sv
`timescale 1ns / 100ps

module Register #(
    parameter unsigned DATA_WIDTH = 16
) (
    input                       write,
    input                       read,
    input                       reset_n,
    input  [             2 : 0] addr_read,
    input  [             2 : 0] addr_write,
    input  [DATA_WIDTH - 1 : 0] data_write,
    output [DATA_WIDTH - 1 : 0] data_read,
    input                       clk
);

    logic [3 * DATA_WIDTH - 1 : 0] register;

    always @(posedge clk) begin
        if (!reset_n) register <= 'b0;
        else if (write) register[DATA_WIDTH*(addr_write-1)+:DATA_WIDTH] <= data_write;
    end

    assign data_read = read ? register[DATA_WIDTH*(addr_read-1)+:DATA_WIDTH] : {DATA_WIDTH{1'hz}};

endmodule

hardware/Processor.sv
`timescale 1ns / 100ps

module Processor #(
    parameter unsigned ADDR_WIDTH = 16,
    parameter unsigned DATA_WIDTH = 16
) (
    output logic [ADDR_WIDTH - 1:0] address,
    inout  logic [DATA_WIDTH - 1:0] data,
    output bit                      read_mem,
    output bit                      write_mem,
    input  bit                      reset_n,
    input  logic                    clk
);

    ////////////////////////  Declaration & Inittialization  ///////////////////////////////
    // Registers & flags
    reg [ADDR_WIDTH - 1 : 0] PC, SP;
    reg [DATA_WIDTH - 1 : 0] MDR, IR;
    logic Z_flag, C_flag;

    // control signals
    logic
        Reg_Write,
        Reg_Read,
        Control_Read,
        IR_Write,
        IR_Read,
        MDR_Read,
        Io_Read,
        Control_Write,
        ALU_In_1,
        ALU_In_2,
        ALU_Out_Write;
    wire  [2:0] PC_Sel;
    logic [3:0] ALU_Op_Sel;
    logic [2 : 0] Reg_Read_Addr, Reg_Write_Addr;

    // interconnect wires & reg
    logic [DATA_WIDTH - 1 : 0] internal_databus;
    logic [ADDR_WIDTH - 1 : 0] next_pc;
    logic [DATA_WIDTH - 1 : 0] ALU_Src_A, ALU_Src_B, ALU_out;

    // ALU
    // Alu alu (
    //     .A_reg     (ALU_Src_A),
    //     .B_reg     (ALU_Src_B),
    //     .op_select (ALU_Op_Sel),
    //     .ALU_output(ALU_out),
    //     .Z_flag    (Z_flag),
    //     .C_flag    (C_flag)
    // );

    // Register File
    Register register (
        .write     (Reg_Write),
        .read      (Reg_Read),
        .reset_n   (reset_n),
        .clk       (clk),
        .data_read (internal_databus),
        .data_write(internal_databus),
        .addr_read (Reg_Read_Addr),
        .addr_write(Reg_Write_Addr)
    );

    // Control Unit
    Control control (
        .reset_n       (reset_n),
        .clk           (clk),
        .MDR           (MDR),
        .Reg_Write     (Reg_Write),
        .Reg_Read      (Reg_Read),
        .Control_Read  (Control_Read),
        .Control_Write (Control_Write),
        .Io_Read       (Io_Read),
        .IR_Write      (IR_Write),
        .IR_Read       (IR_Read),
        .MDR_Read      (MDR_Read),
        .PC_Sel        (PC_Sel),
        .Z_flag        (Z_flag),
        .C_flag        (C_flag),
        .ALU_In_1      (ALU_In_1),
        .ALU_In_2      (ALU_In_2),
        .ALU_Op_Sel    (ALU_Op_Sel),
        .ALU_Out_Write (ALU_Out_Write),
        .Reg_Read_Addr (Reg_Read_Addr),
        .Reg_Write_Addr(Reg_Write_Addr)
    );

    ////////////////////////////////////////////////////////////////////////////////////////

    ////////////////////////  Memory Access  ////////////////////////////

    assign read_mem  = Control_Read ? 1 : 0;
    assign write_mem = Control_Write ? 1 : 0;
    always_comb begin
        if (MDR_Read) MDR = internal_databus;
        if (IR_Write) IR = internal_databus;
    end

    assign internal_databus = read_mem ? data : (ALU_Out_Write ? ALU_out : (IR_Read ? IR : {DATA_WIDTH{1'hz}}));
    assign address = Control_Read ? (Io_Read ? IR : PC) : (Control_Write ? IR : {ADDR_WIDTH{1'hz}});
    assign data = write_mem ? internal_databus : {DATA_WIDTH{1'hz}};

    // always_ff @(posedge clk) begin
    //     if (Control_Read) begin
    //         address  <= Io_Read ? IR : PC;
    //         read_mem <= 1;
    //         if (MDR_Read) MDR <= internal_databus;
    //         if (IR_Write) IR <= internal_databus;
    //     end else begin
    //         read_mem <= 0;
    //     end
    //
    //     if (Control_Write) begin
    //         address   <= IR;
    //         write_mem <= 1;
    //     end else begin
    //         write_mem <= 0;
    //     end
    // end

    //////////////////////////////////////////////////////////////////////

    ////////////////////////  ALU  ////////////////////////////

    // always_comb begin
    //     case (ALU_In_1)
    //         1: ALU_Src_A = internal_databus;
    //         default: begin
    //             ALU_Src_A = {DATA_WIDTH{1'b0}};
    //         end
    //     endcase
    //     case (ALU_In_2)
    //         0: ALU_Src_B = internal_databus;
    //         1: ALU_Src_B = IR;
    //         default: begin
    //             ALU_Src_B = {DATA_WIDTH{1'b0}};
    //         end
    //     endcase
    // end

    ///////////////////////////////////////////////////////////

    ////////////////////////  CPU reset Program Counter ////////////////////////////

    always_comb begin
        case (PC_Sel)
            0: next_pc = PC + {ADDR_WIDTH{1'b0}};
            1: next_pc = PC + 1'b1;
            2: next_pc = Z_flag ? IR : PC + 1'b1;
            3: next_pc = (!Z_flag) ? IR : PC + 1'b1;
            4: next_pc = (C_flag) ? IR : PC + 1'b1;
            5: next_pc = (!C_flag) ? IR : PC + 1'b1;
            default: next_pc = PC + {ADDR_WIDTH{1'b0}};
        endcase
    end

    always_ff @(posedge clk) begin
        if (!reset_n) PC <= {ADDR_WIDTH{1'b0}};
        else PC <= next_pc;
    end

    //////////////////////////////////////////////////////////////////////


endmodule

hardware/Memory.sv
`timescale 1ns / 100ps

module Memory #(
    parameter unsigned ADDR_WIDTH = 16,
    parameter unsigned DATA_WIDTH = 16,
    parameter unsigned DEPTH = 2 ** ADDR_WIDTH
) (
    input logic                  clk,
    input bit                    write,
    input bit                    read,
    input logic [ADDR_WIDTH-1:0] addr,
    inout logic [DATA_WIDTH-1:0] data
);

    logic [DATA_WIDTH-1:0] read_addr;
    logic [DATA_WIDTH-1:0] mem[5];

    always_comb begin
        if (write) mem[addr] = data;
        if (read) read_addr = addr;
    end

    assign data = read ? mem[read_addr] : {DATA_WIDTH{1'hz}};
endmodule

hardware/test_benches/Processor_tb.sv
`timescale 1ns / 100ps

module Processor_tb;
    parameter unsigned ADDR_WIDTH = 16;
    parameter unsigned DATA_WIDTH = 16;


    logic clk, read, write, reset_n;
    logic [ADDR_WIDTH-1:0] addr;
    wire  [DATA_WIDTH-1:0] data;

    Memory memory (
        .write(write),
        .read (read),
        .clk  (clk),
        .addr (addr),
        .data (data)
    );

    Processor u0 (
        .address  (addr),
        .data     (data),
        .read_mem (read),
        .write_mem(write),
        .clk      (clk),
        .reset_n  (reset_n)
    );



    always #1 clk = ~clk;

    initial begin
        clk     = 1;
        reset_n = 1;
        $readmemh("memory.hex", memory.mem, 0);

        #3 reset_n = 0;
        #2 reset_n = 1;
        u0.register.register_file <= 64'h0000000BDEADCAFE;

        #60 $finish;
    end
    initial begin
        $dumpfile("waveform.vcd");
        $dumpvars;
    end

endmodule

hardware/test_benches/waveform.vcd
$version Generated by VerilatedVcd $end
$timescale 100ps $end
 $scope module TOP $end
  $scope module Processor_tb $end
   $var wire 32 N ADDR_WIDTH [31:0] $end
   $var wire 32 N DATA_WIDTH [31:0] $end
   $var wire 1 D clk $end
   $var wire 1 # read $end
   $var wire 1 $ write $end
   $var wire 1 E reset_n $end
   $var wire 16 8 addr [15:0] $end
   $var wire 16 F data [15:0] $end
   $scope module memory $end
    $var wire 32 N ADDR_WIDTH [31:0] $end
    $var wire 32 N DATA_WIDTH [31:0] $end
    $var wire 32 O DEPTH [31:0] $end
    $var wire 1 D clk $end
    $var wire 1 $ write $end
    $var wire 1 # read $end
    $var wire 16 8 addr [15:0] $end
    $var wire 16 F data [15:0] $end
    $var wire 16 9 read_addr [15:0] $end
    $var wire 16 G mem[0] [15:0] $end
    $var wire 16 H mem[1] [15:0] $end
    $var wire 16 I mem[2] [15:0] $end
    $var wire 16 J mem[3] [15:0] $end
    $var wire 16 K mem[4] [15:0] $end
   $upscope $end
   $scope module u0 $end
    $var wire 32 N ADDR_WIDTH [31:0] $end
    $var wire 32 N DATA_WIDTH [31:0] $end
    $var wire 16 8 address [15:0] $end
    $var wire 16 F data [15:0] $end
    $var wire 1 # read_mem $end
    $var wire 1 $ write_mem $end
    $var wire 1 E reset_n $end
    $var wire 1 D clk $end
    $var wire 16 @ PC [15:0] $end
    $var wire 16 P SP [15:0] $end
    $var wire 16 3 MDR [15:0] $end
    $var wire 16 4 IR [15:0] $end
    $var wire 1 Q Z_flag $end
    $var wire 1 R C_flag $end
    $var wire 1 % Reg_Write $end
    $var wire 1 & Reg_Read $end
    $var wire 1 # Control_Read $end
    $var wire 1 ' IR_Write $end
    $var wire 1 ( IR_Read $end
    $var wire 1 ) MDR_Read $end
    $var wire 1 * Io_Read $end
    $var wire 1 $ Control_Write $end
    $var wire 1 + ALU_In_1 $end
    $var wire 1 , ALU_In_2 $end
    $var wire 1 - ALU_Out_Write $end
    $var wire 3 . PC_Sel [2:0] $end
    $var wire 4 / ALU_Op_Sel [3:0] $end
    $var wire 3 0 Reg_Read_Addr [2:0] $end
    $var wire 3 1 Reg_Write_Addr [2:0] $end
    $var wire 16 L internal_databus [15:0] $end
    $var wire 16 M next_pc [15:0] $end
    $var wire 16 S ALU_Src_A [15:0] $end
    $var wire 16 T ALU_Src_B [15:0] $end
    $var wire 16 U ALU_out [15:0] $end
    $scope module control $end
     $var wire 32 N DATA_WIDTH [31:0] $end
     $var wire 1 E reset_n $end
     $var wire 1 D clk $end
     $var wire 16 3 MDR [15:0] $end
     $var wire 1 Q Z_flag $end
     $var wire 1 R C_flag $end
     $var wire 1 & Reg_Read $end
     $var wire 3 0 Reg_Read_Addr [2:0] $end
     $var wire 1 % Reg_Write $end
     $var wire 3 1 Reg_Write_Addr [2:0] $end
     $var wire 1 # Control_Read $end
     $var wire 1 $ Control_Write $end
     $var wire 1 * Io_Read $end
     $var wire 1 ' IR_Write $end
     $var wire 1 ( IR_Read $end
     $var wire 1 ) MDR_Read $end
     $var wire 3 . PC_Sel [2:0] $end
     $var wire 1 + ALU_In_1 $end
     $var wire 1 , ALU_In_2 $end
     $var wire 4 / ALU_Op_Sel [3:0] $end
     $var wire 1 - ALU_Out_Write $end
     $var wire 4 : rom_addr [3:0] $end
     $var wire 24 2 CTRL [23:0] $end
     $var wire 4 5 param_2 [3:0] $end
     $var wire 4 6 param_1 [3:0] $end
     $var wire 4 ; write_addr [3:0] $end
     $var wire 4 < read_addr [3:0] $end
     $var wire 8 7 instr [7:0] $end
     $var wire 8 A state [7:0] $end
     $var wire 8 = next_state [7:0] $end
     $scope module rom $end
      $var wire 4 : rom_addr [3:0] $end
      $var wire 4 < read_addr [3:0] $end
      $var wire 4 ; write_addr [3:0] $end
      $var wire 24 2 CTRL [23:0] $end
      $var wire 4 > read_reg_addr [3:0] $end
      $var wire 4 ? write_reg_addr [3:0] $end
      $var wire 24 V memory[0] [23:0] $end
      $var wire 24 W memory[1] [23:0] $end
      $var wire 24 X memory[2] [23:0] $end
      $var wire 24 Y memory[3] [23:0] $end
      $var wire 24 Z memory[4] [23:0] $end
      $var wire 24 [ memory[5] [23:0] $end
      $var wire 24 \ memory[6] [23:0] $end
      $var wire 24 ] memory[7] [23:0] $end
      $var wire 24 ^ memory[8] [23:0] $end
      $var wire 24 _ memory[9] [23:0] $end
      $var wire 24 ` memory[10] [23:0] $end
     $upscope $end
    $upscope $end
    $scope module register $end
     $var wire 32 N DATA_WIDTH [31:0] $end
     $var wire 1 % write $end
     $var wire 1 & read $end
     $var wire 1 E reset_n $end
     $var wire 3 0 addr_read [2:0] $end
     $var wire 3 1 addr_write [2:0] $end
     $var wire 16 L data_write [15:0] $end
     $var wire 16 L data_read [15:0] $end
     $var wire 1 D clk $end
     $var wire 48 B register [47:0] $end
    $upscope $end
   $upscope $end
  $upscope $end
 $upscope $end
$enddefinitions $end


#0
1#
0$
0%
0&
0'
0(
1)
0*
0+
0,
0-
b001 .
b0000 /
b000 0
b000 1
b000000001000010010000000 2
b0000000000000000 3
b0000000000000000 4
b0000 5
b0000 6
b00000000 7
b0000000000000000 8
b0000000000000000 9
b0000 :
b0000 ;
b0000 <
b00000001 =
b1010 >
b1010 ?
b0000000000000000 @
b00000000 A
b000000000000000000000000000000000000000000000000 B
1D
1E
b0000000000000000 F
b0000000000000000 G
b0000000100100100 H
b1100101011111110 I
b0000000100010010 J
b1111111111111111 K
b0000000000000000 L
b0000000000000001 M
b00000000000000000000000000010000 N
b00000000000000010000000000000000 O
b0000000000000000 P
0Q
0R
b0000000000000000 S
b0000000000000000 T
b0000000000000000 U
b000000001000010010000000 V
b100010000000000000000000 W
b000000001001000010000000 X
b000010000000100000000000 Y
b001100000000000000000000 Z
b001000000000000000000000 [
b000100000000000000000000 \
b000000110000000000000000 ]
b000000100000000000000000 ^
b000000010000000000000000 _
b000000000000000000000000 `
#10
0D
#20
0#
0)
b000 .
b000000000000000000000000 2
b0000000000000001 9
b1010 :
b00000000 =
b0000000000000001 @
b00000001 A
1D
#30
0D
#40
1#
1)
b001 .
b000000001000010010000000 2
b0000000100100100 3
b0100 5
b0010 6
b00000001 7
b0000000000000001 8
b0000 :
b00000001 =
b00000000 A
1D
b0000000100100100 F
b0000000100100100 L
b0000000000000010 M
#50
0D
0E
#60
0#
0)
b000 .
b000000000000000000000000 2
b0000000000000000 8
b0000000000000000 9
b1010 :
b00000000 =
b0000000000000000 @
b11111111 A
1D
b0000000000000000 F
b0000000000000000 L
b0000000000000000 M
#70
0D
#80
1D
#90
0D
#100
1#
1)
b001 .
b000000001000010010000000 2
b0000000000000000 3
b0000 5
b0000 6
b00000000 7
b0000 :
b00000001 =
b00000000 A
1D
1E
b0000000000000001 M
#110
0D
#120
0#
0)
b000 .
b000000000000000000000000 2
b0000000000000001 9
b1010 :
b00000000 =
b0000000000000001 @
b00000001 A
1D
#130
0D
#140
1#
1)
b001 .
b000000001000010010000000 2
b0000000100100100 3
b0100 5
b0010 6
b00000001 7
b0000000000000001 8
b0000 :
b00000001 =
b00000000 A
1D
b0000000100100100 F
b0000000100100100 L
b0000000000000010 M
#150
0D
#160
1'
0)
b000000001001000010000000 2
b1100101011111110 4
b0000000000000010 8
b0000000000000010 9
b0010 :
b00000010 =
b0000000000000010 @
b00000001 A
1D
b1100101011111110 F
b1100101011111110 L
b0000000000000011 M
#170
0D
#180
0#
1%
0'
1(
b000 .
b010 1
b000010100000100000000000 2
b0000000000000000 8
b0000000000000011 9
b0011 :
b0010 ;
b00000000 =
b1000 ?
b0000000000000011 @
b00000010 A
1D
b0000000000000000 F
#190
0D
#200
1#
0%
0(
1)
b001 .
b000 1
b000000001000010010000000 2
b0000000100010010 3
b0010 5
b0001 6
b0000000000000011 8
b0000 :
b0000 ;
b00000001 =
b1010 ?
b00000000 A
b000000000000000011001010111111100000000000000000 B
1D
b0000000100010010 F
b0000000100010010 L
b0000000000000100 M
#210
0D
#220
0#
1%
1&
0)
b000 .
b010 0
b001 1
b101010010000000000000000 2
b0000000000000000 8
b0000000000000100 9
b0001 :
b0001 ;
b0010 <
b00000000 =
b0101 >
b1001 ?
b0000000000000100 @
b00000001 A
1D
b0000000000000000 F
b1100101011111110 L
#230
0D
#240
1#
0%
0&
1)
b001 .
b000 0
b000 1
b000000001000010010000000 2
b1111111111111111 3
b1111 5
b1111 6
b11111111 7
b0000000000000100 8
b0000 :
b0000 ;
b0000 <
b00000001 =
b1010 >
b1010 ?
b00000000 A
b000000000000000011001010111111101100101011111110 B
1D
b1111111111111111 F
b1111111111111111 L
b0000000000000101 M
#250
0D
#260
0#
0)
b000 .
b000000000000000000000000 2
b0000000000000000 8
b0000000000000101 9
b1010 :
b00000000 =
b0000000000000101 @
b00000001 A
1D
b0000000000000000 F
b0000000000000000 L
#270
0D
#280
1#
1)
b001 .
b000000001000010010000000 2
b0000000000000000 3
b0000 5
b0000 6
b00000000 7
b0000000000000101 8
b0000 :
b00000001 =
b00000000 A
1D
b0000000000000110 M
#290
0D
#300
0#
0)
b000 .
b000000000000000000000000 2
b0000000000000000 8
b0000000000000110 9
b1010 :
b00000000 =
b0000000000000110 @
b00000001 A
1D
#310
0D
#320
1#
1)
b001 .
b000000001000010010000000 2
b0000000000000110 8
b0000 :
b00000001 =
b00000000 A
1D
b0000000000000111 M
#330
0D
#340
0#
0)
b000 .
b000000000000000000000000 2
b0000000000000000 8
b0000000000000111 9
b1010 :
b00000000 =
b0000000000000111 @
b00000001 A
1D
#350
0D
#360
1#
1)
b001 .
b000000001000010010000000 2
b0000000000000111 8
b0000 :
b00000001 =
b00000000 A
1D
b0000000000001000 M
#370
0D
#380
0#
0)
b000 .
b000000000000000000000000 2
b0000000000000000 8
b0000000000001000 9
b1010 :
b00000000 =
b0000000000001000 @
b00000001 A
1D
#390
0D
#400
1#
1)
b001 .
b000000001000010010000000 2
b0000000000001000 8
b0000 :
b00000001 =
b00000000 A
1D
b0000000000001001 M
